{"cp-ffa0f6a3":[{"t":"巡衣錦軍製還鄉歌","f":"other","p":["三節還鄉兮挂錦衣，碧天朗朗兮愛日暉。","功成道上兮列旌旗，父老遠來兮相追隨。","家山鄉眷兮會時稀，今朝設宴兮觥散飛。","斗牛無孛兮民無欺，吳越一王兮駟馬歸。"]},{"t":"沒了期歌 一","f":"other","p":["沒了期，沒了期，營基纔了又倉基。"]},{"t":"沒了期歌 二","f":"other","p":["沒了期，沒了期，春衣纔了又冬衣。"]},{"t":"句","f":"other","p":["須將一片地，付與有心人。","黃河信有澄清日，後代應難繼此才。","傳語龍王幷水府，錢塘借與築錢城。"]}],"cp-487cd1a6":[{"t":"安德山池宴集","f":"other","p":["伏櫪丹霞外，遮園煥景舒。","行雲泛層阜，蔽月下清渠。","亭中奏趙瑟，席上舞燕裾。","花落春鶯晚，風光夏葉初。","良朋比蘭蕙，雕藻邁瓊琚。","獨有狂歌客，來承歡宴餘。"]},{"t":"遼東侍宴山夜臨秋同賦臨韻應詔","f":"other","p":["涿野軒皇陳，丹浦帝堯心。","彎弧射封豕，解網縱前禽。","慿高御爽節，流月揚清陰。","霧匝長城險，雲歸渤澥深。","飜垗入層漢，落雁警遥岑。","露條疏更響，涼蟬寂不吟。","三韓初静亂，八桂始披襟。","商飚泛輕武，自澗引衣簮。","酒漾投川醁，歌傳芳樹音。","邊烽良永□，麾旆竦成林。"]},{"t":"春日侍宴望海應詔","f":"other","p":["從軍渡蓬海，萬里正蒼蒼。","縈波迴地軸，激浪上天潢。","夕雲類鵬徙，春濤疑蓋張。","天吳静無際，金駕儼成行。","戈船凌白日，鞭石[耿]（秋）虹梁。","電舉[朝]（潮）宗外，風驅韓貊鄉。","之罘初播雨，遼碣始分光。","麾城湛□□，□□□□□。","同文漸邊服，入塞佇歌倡。","（據《翰林學士集》校改。","）。"]},{"t":"奉和行經破薛舉戰地應詔","f":"other","p":["王功先美化，帝略蘊戎昭。","魚驪（友人蔣禮來同志謂當作魚麗，本《左傳》。","）入丹浦，龍戰起鳴條。","長劍星光落，高旗月影搖。","（《翰林學士集》此句缺「摇」字。","）昔往摧勍寇，今巡奏短簫。","旌門麗霜景，帳殿含秋飇。","□池水未結，（「□池」，《翰林學士集》作「□沲」，上字下半殘存，疑爲「河」字。","）官渡柳初凋。","邊烽夕霧卷，關陳曉雲銷。","鴻名兼轍跡，至聖俯唐堯。","睿藻煙霞焕，天聲宮羽調。","平分共飲德，率土更聞韶。","（以上三詩載《武林往哲遺著》。","）（以上三詩皆出日本尾張國真福寺藏唐卷子本《翰林學士集》。","此集清末田貴陽陳田攜歸影刻傳世。","）。"]},{"t":"湘潭偶題詩","f":"other","p":["遠山酋萃（友人蔣禮垗同志謂當作「𡺚崒」。","）翠凝烟，爛漫桐花二月天。","游徧九衢燈火夜，歸來月挂海棠前。","（此詩載《槐廬叢書》、《金石錄補》卷二十二。","《全唐詩續補遺》卷一據《佘山詩話》錄此詩，今刪去。","首句「酋萃」二字，《佘山詩話》正作「𡺚崒」，與蔣說合。","明陳繼儒《妮古錄》卷一謂宋咸淳中邑令趙必穆於池中得斷碑，上刻此詩。","首句二字亦作「𡺚崒」。","錄此詩後云「餘皆莫辨」。","）（〖1〗《槐廬叢書》、《金石錄補》按此爲褚遂良貶潭州都督時所作。","）。"]}],"cp-702cd443":[{"t":"奉和受圖溫洛應制","f":"other","p":["八神扶玉輦，六羽警瑤谿。","戒道伊川北，通津澗水西。","御圖開洛匱，刻石與天齊。","瑞日波中上，仙禽霧裏低。","微臣矯羽翮，抃舞接鸞鷖。"]}],"cp-7dd4f848":[{"t":"詠銅柱","f":"other","p":["天門街裏倒天樞，火急先須卸火珠。","計合一條絲線挽，何勞兩縣索人夫。"]},{"t":"詠毀天樞","f":"other","p":["天門街上倒天樞，火急先須卸火珠。","計合一條麻線挽，何勞兩縣索人夫。"]},{"t":"過王濬墓（二首）","f":"other","p":["。"]},{"t":"過王濬墓（二首） 一","f":"other","p":["青史高遺迹，黃壚掩舊封。","寧知陌上□[一]，（項云據《晉書·羊祜傳》，當補「獸」字。","）何羨水中龍。"]},{"t":"過王濬墓（二首） 二","f":"other","p":["樵採徒爲禁，英威豈得從。","定知[□]路蟻，（項疑闕字在「路」字下。","）不畏水中龍。","（[一]劉疑「虎」字。","）。"]}],"cp-39d0361b":[{"t":"寄興國池鶴上劉相公","f":"other","p":["馴狎經時久，䙰褷短翮存。","不隨淮海變，空媿稻粱恩。","獨立秋天靜，單棲夕露繁。","欲飛還斂翼，詎敢望乘軒。"]},{"t":"送李司直使吳","f":"other","p":["使臣方擁傳，王事遠辭家。","震澤逢殘雨，新豐過落花。","水萍千葉散，風柳萬條斜。","何處看離恨，春江無限沙。"]},{"t":"送李觀之宣州謁袁中丞賦得三州渡","f":"other","p":["古渡大江濱，西南距要津。","自當舟檝路，應濟往來人。","翻浪驚飛鳥，回風起綠蘋。","君看波上客，歲晚獨垂綸。"]}],"cp-206abb6d":[{"t":"和于中丞夏杪登越王樓望雪山見寄","f":"other","p":["志乖多感物，臨眺更增愁。","暑候雖云夏，江聲已似秋。","雪遙難辨木，村近好維舟。","莫恨歸朝晚，朝簪擬勝遊。"]}],"cp-0893f55c":[{"t":"題青龍精舍","f":"other","p":["壽夭雖云命，榮枯亦大偏。","不知雷氏劒，何處更衝天。"]}],"cp-70cbb28f":[{"t":"摘紫芝","f":"other","p":["偶游洞府到芝田，星月茫茫欲曙天。","雖則似離塵世了，不知何處偶真仙。"]},{"t":"玉女舞霓裳","f":"other","p":["舞勢隨風散復收，歌聲似磬韻還幽。","千迴赴節填詞處，嬌眼如波入鬢流。"]}],"cp-ecc490f9":[{"t":"示妓牓子","f":"other","p":["綠羅帬下標三棒，紅粉顋邊淚兩行。","叉手向前咨大使，這迴不敢惱兒郎。"]},{"t":"又留別同院","f":"other","p":["憶昔當年富貴時，如今頭腦尚依稀。","布袍破後思宮內，錦袴穿時憶御衣。","鶻子背鑽高力士，嬋娟飜畫太真妃。","如今顦顇離南海，恰似當時幸蜀時。"]}],"cp-cdea8292":[{"t":"失題","f":"other","p":["故國海雲端，歸寧便整鞍。","里榮身上蒨，省罷手中蘭。","燒急平蕪廣，風悲古木寒。","謝公山色在，朝夕共誰觀。"]}],"cp-d6294d8a":[{"t":"定西番","f":"other","p":["蒼翠濃陰滿院，鶯對語。","蝶交飛，戲薔薇。","斜日倚闌風好，餘香出繡衣。","未得玉郎消息，幾時歸。"]},{"t":"何滿子 一","f":"other","p":["寂寞芳菲暗度，歲華如箭堪驚。","緬想舊歡多少事，轉添春思難平。","曲檻絲垂金柳，小窗弦斷銀箏。","深院空聞燕語，滿園閑落花輕。","一片相思休不得，忍教長日愁生。","誰見夕陽孤夢，覺來無限傷情。"]},{"t":"何滿子 二","f":"other","p":["無語殘妝澹薄，含羞嚲袂輕盈。","幾度香閨眠過曉，綺窗疎日微明。","雲母帳中偷惜，水精枕上初驚。","笑靨嫩疑花拆，愁眉翠歛山橫。","相望只教添悵恨，整鬟時見纖瓊。","獨倚朱扉閑立，誰知別有深情。"]},{"t":"女冠子 一","f":"other","p":["碧桃紅杏，遲日媚籠光影，綵霞深。","香暖熏鶯語，風清引鶴音。","翠鬟冠玉葉，霓袖捧瑤琴。","應共吹簫侶，暗相尋。"]},{"t":"女冠子 二","f":"other","p":["修蛾慢臉，不語檀心一點，小山妝。","蟬鬢低含綠，羅衣澹拂黃。","[悶]來深院裏，閑步落花傍。","纖手輕輕整，玉爐香。"]},{"t":"酒泉子 一","f":"other","p":["閑臥繡幃，慵想萬般情寵。","錦檀偏，翹股重，翠雲欹。","暮天屏上春山碧，映香煙霧隔。","蕙蘭心，魂夢役，歛蛾眉。"]},{"t":"酒泉子 二","f":"other","p":["鈿匣舞鸞，隱映豔紅修碧。","月梳斜，雲鬢膩，粉香寒。","曉花微斂輕呵展，嫋釵金燕輭。","日初升，簾半卷，對妝殘。"]},{"t":"浣溪沙 一","f":"other","p":["春暮黃鶯下砌前，水精簾影露珠懸，綺霞低映晚晴天。","弱柳萬條垂翠帶，殘紅滿地碎香鈿，蕙風飄蕩散輕煙。"]},{"t":"浣溪沙 二","f":"other","p":["花榭香紅煙景迷，滿庭芳草綠萋萋，金鋪閑掩繡簾底。","紫燕一雙嬌語碎，翠屏十二晚峰齊，夢魂消散醉空閨。"]},{"t":"浣溪沙 三","f":"other","p":["晚起紅房醉欲消，綠鬟雲散嫋金翹，雪香花語不勝嬌。","好是向人柔弱處，玉纖時急繡帬腰，春心牽惹轉無憀。"]},{"t":"浣溪沙 四","f":"other","p":["一隻橫釵墜髻叢，靜眠珍簟起來慵，繡羅紅嫩抹蘇胸。","羞歛細蛾魂暗斷，因迷無語思猶濃，小屏香靄碧山重。"]},{"t":"浣溪沙 五","f":"other","p":["雲薄羅帬綬帶長，滿身新裛瑞龍香，翠鈿斜映豔梅妝。","佯不覷人空婉約，笑和嬌語太猖狂，忍教牽恨暗形相。"]},{"t":"浣溪沙 六","f":"other","p":["碧玉冠輕嫋燕釵，捧心無語步香階，緩移弓底繡羅鞋。","暗想歡娛何計好，豈堪期約有時乖，日高深院正忘懷。"]},{"t":"浣溪沙 七","f":"other","p":["半醉凝情臥繡茵，睡容無力卸羅裙，玉籠鸚鵡厭聽聞。","慵整落釵金翡翠，象梳欹鬢月生雲，錦屏綃幌麝煙薰。"]},{"t":"後庭花 一","f":"other","p":["鶯啼燕語芳菲節，瑞庭花發。","昔時歡宴歌聲揭，管弦清越。","自從陵谷追遊歇，畫梁塵黦。","傷心一片如珪月，閑鎖宮闕。"]},{"t":"後庭花 二","f":"other","p":["輕盈舞伎含芳豔，競妝新臉。","步搖珠翠修蛾歛，膩鬟雲染。","歌聲慢發開檀點，繡衫斜掩。","時將纖手勻紅臉，笑拈金靨。"]},{"t":"後庭花 三","f":"other","p":["越羅小袖新香蒨，薄籠金釧。","倚闌無語搖輕扇，半遮勻面。","春殘日暖鶯嬌嬾，滿庭花片。","爭不教人長相見，畫堂深院。"]},{"t":"菩薩蠻 一","f":"other","p":["梨花滿院飄香雪，高樓夜靜風箏咽。","斜月照簾帷，憶君和夢稀。","小窗燈影背，燕語驚愁態。","屏掩斷香飛，行雲山外歸。"]},{"t":"菩薩蠻 二","f":"other","p":["繡簾高軸臨塘看，雨翻荷芰真珠散。","殘暑晚初涼，輕風渡水香。","無憀悲往事，爭那牽情思。","光影暗相催，等閑秋又來。"]},{"t":"菩薩蠻 三","f":"other","p":["天含殘碧融春色，五陵薄倖無消息。","盡日掩朱門，離愁暗斷魂。","鶯啼芳樹暖，燕拂回塘滿。","寂寞對屏山，相思醉夢間。"]},{"t":"清平樂","f":"other","p":["春光欲暮，寂寞閑庭戶。","粉蝶雙雙穿檻舞，簾卷晚天疎雨。","含愁獨倚閨幃，玉爐煙斷香微。","正是銷魂時節，東風滿院花飛。"]},{"t":"更漏子 一","f":"other","p":["秋色清，河影淡，深戶燭寒光暗。","綃幌碧，錦衾紅，博山香炷融。","更漏咽，蛩鳴切，滿院霜華如雪。","新月上，薄雲收，映簾懸玉鉤。"]},{"t":"更漏子 二","f":"other","p":["煙月寒，秋夜靜，漏轉金壺初永。","羅幕下，繡屏空，燈花結碎紅。","人悄悄，愁無了，思夢不成難曉。","長憶得，與郎期，竊香私語時。"]},{"t":"南歌子 一","f":"other","p":["遠山愁黛碧，橫波慢臉明，膩香紅玉茜羅輕。","深院晚堂人靜，理銀箏。","鬢動行雲影，帬遮點屐聲，嬌羞愛問曲中名。","楊柳杏花時節，幾多情。"]},{"t":"南歌子 二","f":"other","p":["惹恨還添恨，牽腸即斷腸，凝情不語一枝芳。","獨映畫簾閑立，繡衣香。","暗想爲雲女，應憐傅粉郎，晚來輕步出閨房。","髻慢釵橫無力，縱猖狂。"]},{"t":"木蘭花","f":"other","p":["掩朱扉，鉤翠箔，滿院鶯聲春寂寞。","勻粉淚，恨檀郎，一去不歸花又落。","對斜暉，臨小閣，前事豈堪重想著。","金帶冷，畫屏幽，寶帳慵熏蘭麝薄。"]},{"t":"小重山","f":"other","p":["梁燕雙飛畫閣前，寂寥多少恨，嬾孤眠。","曉來閑處想君憐，紅羅帳，金鴨冷沈煙。","誰信損嬋娟，倚屏啼玉筯，溼香鈿。","四支無力上鞦韆，羣花謝，愁對豔陽天。"]},{"t":"臨江仙 一","f":"other","p":["南齊天子寵嬋娟，六宮羅綺三千，潘妃嬌豔獨芳妍。","椒房蘭洞，雲雨降神仙。","縱態迷歡心不足，風流可惜當年，纖腰婉約步金蓮。","妖君傾國，猶自至今傳。"]},{"t":"臨江仙 二","f":"other","p":["幽閨欲曙聞鶯轉，紅窗月影微明，好風頻謝落花聲。","隔幃殘燭，猶照綺屏箏。","繡被錦茵眠玉煖，炷香斜嫋煙輕，淡蛾羞斂不勝情。"]}],"cp-a01876e0":[{"t":"句","f":"other","p":["藤拂石溪流水淨，風來雲寺過鐘微。"]}],"cp-11fdd9b8":[{"t":"同竇羣雪中寓直（題擬）","f":"other","p":["耿耿風雪暮，直廬未掩扉。","詠蘭幽助興，儷玉粲相輝。","氣勁琴韻切，夜深鑪火微。","雖殊江海遠，即此戀彤闈。","（見《竇氏聯珠集》。","題下原署「吏部員外郎韋貫之」）。"]}],"cp-eaa0a133":[{"t":"导引","f":"other","p":["忆玉清景，繁盛极当时。","千古事难追。","汉家别庙秋风起，空出奉宸衣。","三山浮海日晖晖。","羽盖共云飞。","灵宫旧是栖真处，还望玉舆归。"]},{"t":"发引","f":"other","p":["玉宸朝晚，忽掩赭黄衣。","愁雾锁金扉。","蓬莱待得仙丹至，人世已成非。","龙轩天仗转西畿。","旌旆入云飞。","望陵宫女垂红泪，不见翠舆归。"]},{"t":"发引","f":"other","p":["上林春晚，曾是奉宸游。","水殿戏龙舟。","玉箫吹断催仙驭，一去隔千秋。","游人重到曲江头。","事往涕难收。","空馀御幄传觞处，依旧水东流。"]},{"t":"倦寻芳慢・倦寻芳","f":"other","p":["露晞向晚，帘幕风轻，小院闲昼。","翠迳莺来，惊下乱红铺绣。","倚危墙，登高榭，海棠经雨胭脂透。","算韶华，又因循过了，清明时候。","倦游燕、风光满目，好景良辰，谁共携手。","恨被榆钱，买断两眉长斗。","忆高阳，人散后。","落花流水仍依旧。","这情怀，对东风、尽成消瘦。"]},{"t":"望江南・忆江南","f":"other","p":["三杰后，福寿两无涯。","食乳相君功未既，妩眉京兆眷方兹。","富贵莫推辞。","门两戟，却棹一纶丝。","莼菜秋风鲈鲙美，桃花春水鳜鱼肥。","笑傲霅溪湄。"]},{"t":"祝英台近","f":"other","p":["柳烟浓，花露重，合是醉时候。","楼倚花梢，长记小垂手。","谁教钗燕轻分，镜鸾慵舞，是孤负、几番春昼。","自别后。","闻道花底花前，多是两眉皱。","又说新来，比似旧时瘦。","须知两意长存，相逢终有。","莫谩被、春光僝僽。"]},{"t":"夜行船","f":"other","p":["曲水溅裙三月二。","马如龙、钿车如水。","风扬游丝，日烘晴昼，人共海棠俱醉。","客里光阴难可意。","扫芳尘、旧游谁记。","午梦醒来，小窗人静，春在卖花声里。"]}],"cp-7f5ac8a7":[{"t":"临江仙","f":"other","p":["冬看山林萧疏净，春来地润花浓。","少年衰老与山同。","世间争名利，富贵与贫穷。","荣贵非干长生药，清闲是不死门风。","劝君识取主人公。","单方只一味，尽在不言中。"]},{"t":"南乡子","f":"other","p":["人有几何般。","富贵荣华总是闲。","自古英雄都如梦，为官。","宝玉妻男宿业缠。","年迈衰残。","鬓发苍浪骨髓乾。","不道山林有好处，贪欢。","只恐痴迷误了贤。"]}],"cp-90c9fa91":[{"t":"蓦山溪","f":"other","p":["醉魂离梦，捻合难成片。","恶味怕黄昏，更西风，梧桐深院。","蝉松翠妩，记那日相逢，情缱绻。","语玲珑，人静凌波见。","香云曾约，念阻题红怨。","应是绿窗寒，也思郎、云衣谁换。","郎今销黯，步楚竹江空，云缥缈，水弥茫，不抵相思半。"]}],"cp-3c409b28":[{"t":"柳梢青","f":"other","p":["露冷仙梯。","霓裳散舞，记取人归。","月度层霄，雨连深夜，谁管花飞。","金铺满地苔衣。","似一片、斜阳未移。","生怕清香，又随凉信，吹过东篱。"]},{"t":"相思引","f":"other","p":["冰箔纱帘小院清。","晴尘不动地花平。","昨宵风雨，凉到木樨屏。","香月照妆秋粉薄，水云飞佩藕丝轻。","好天良夜，闲理玉靴笙。"]},{"t":"西江月","f":"other","p":["夜半河痕依约，雨馀天气冥濛。","起行微月遍池东。","水影浮花、花影动帘栊。","量减难追醉白，恨长莫尽题红。","雁声能到画楼中。","也要玉人、知道有秋风。"]},{"t":"清平乐","f":"other","p":["柳丝摇露。","不绾兰舟住。","人宿溪桥知那处。","一夜风声千树。","晓楼望断天涯。","过鸿影落寒沙。","可惜些儿秋意，等闲过了黄花。"]},{"t":"好事近","f":"other","p":["春色醉酴醿，昼永篆烟初绝。","临水杨花千树，尽一时飞雪。","穿帘度竹弄轻盈，东风老犹劣。","睡起凭栏无绪，听几声啼鴂。"]}]}