{"cp-bf65e0a7":[{"t":"郊廟歌辭 儀坤廟樂章 昭升","f":"other","p":["陽靈配德，陰魄昭升。","堯壇鳳下，漢室龍興。","俔天作對，前旒是凝。","化行南國，道盛西陵。","造舟集灌，無德而稱。","我粢既絜，我醴既澄。","陰陰靈廟，光靈若憑。","德馨惟享，孝思烝烝。"]},{"t":"儀坤廟樂章二首 一","f":"other","p":["陽靈配德，陰魄昭升。","堯壇鳳下，漢室龍興。","俔天作對，前旒是凝。","化行南國，道盛西陵。","造舟集灌，無德而稱。","我粢既潔，我醴既澄。","陰陰靈廟，光靈若憑。","德馨惟饗，孝思烝烝。"]},{"t":"儀坤廟樂章二首 二","f":"other","p":["乾道既亨，坤元以貞。","肅雍攸在，輔佐斯成。","外睦九族，內光一庭。","克生睿哲，祚我休明。","欽若徽範，悠哉淑靈。","建茲清宮，於彼上京。","縮茅以獻，絜秬惟馨。","實受其福，斯乎億齡。"]},{"t":"九日幸臨渭亭登高應制得曆字","f":"other","p":["暮節乘原野，宣遊俯崖壁。","秋登華實滿，氣嚴鷹隼擊。","仙菊含霜泛，聖藻臨雲錫。","願陪九九辰，長奉千千曆。"]},{"t":"慈恩寺九日應制","f":"other","p":["寶宮星宿劫，香塔鬼神功。","王遊盛塵外，睿覽出區中。","日宇開初景，天詞掩大風。","微臣謝時菊，薄采入芳叢。"]},{"t":"早春魚亭山","f":"other","p":["春氣動百草，紛榮時斷續。","白雲自高妙，裴回空山曲。","陽林花已紅，寒澗苔未綠。","伊余息人事，蕭寂無營欲。","客行雖云遠，翫之聊自足。"]},{"t":"秋日還京陝西十里作","f":"other","p":["驅車越陝郊，北顧臨大河。","隔河望鄉邑，秋風水增波。","西登咸陽途，日暮憂思多。","傅巖既紆鬱，首山亦嵯峨。","操築無昔老，採薇有遺歌。","客遊節回換，人生知幾何。"]},{"t":"奉和送金城公主適西蕃應制","f":"other","p":["天道寧殊俗，慈仁乃戢兵。","懷荒寄赤子，忍愛鞠蒼生。","月下瓊娥去，星分寶婺行。","關山馬上曲，相送不勝情。"]},{"t":"春日登樓野望","f":"other","p":["憑軒聊一望，春色幾芬菲。","野外煙初合，樓前花正飛。","嬌鶯弄新響，斜日散餘暉。","誰忍孤遊客，言念獨依依。"]},{"t":"餞許州宋司馬赴任","f":"other","p":["令弟與名兄，高才振兩京。","別序聞鴻燕，離章動鶺鴒。","遠朋馳翰墨，勝地寫丹青。","風月相思夜，勞望潁川星。"]},{"t":"奉和聖製春日幸望春宮應制","f":"other","p":["九春風景足林泉，四面雲霞敞御筵。","花鏤黃山繡作苑，草圖玄灞錦爲川。","飛觴競醉心迴日，走馬爭先眼著鞭。","喜奉仙遊歸路遠，直言行樂不言旋。"]},{"t":"奉和幸安樂公主山莊應制","f":"other","p":["主家園囿極新規，帝郊遊豫奉天儀。","歡宴瑤臺鎬京集，賞賜銅山蜀道移。","曲閣交映金精板，飛花亂下珊瑚枝。","借問今朝八龍駕，何如昔日望仙池。"]},{"t":"秋朝覽鏡","f":"other","p":["客心驚落木，夜坐聽秋風。","朝日看容鬢，生涯在鏡中。"]},{"t":"夜宴安樂公主新宅","f":"other","p":["秦樓宴喜月裴回，妓筵銀燭滿庭開。","坐中香氣排花出，扇後歌聲逐酒來。"]},{"t":"餞唐永昌","f":"other","p":["河洛風煙壯市朝，送君飛鳧去漸遙。","更思明年桃李月，花紅柳綠宴浮橋。"]}],"cp-42ae092c":[{"t":"九日幸臨渭亭登高應制得酒字","f":"other","p":["睿賞叶通三，宸遊契重九。","蘭將葉布席，菊用香浮酒。","落日下桑榆，秋風歇楊柳。","幸齊東戶慶，希薦南山壽。"]},{"t":"奉和九月九日登慈恩寺浮圖應制","f":"other","p":["季月啓重陽，金輿陟寶坊。","御旗橫日道，仙塔儼雲莊。","帝蹕千官從，乾詞七曜光。","顧慙文墨職，無以頌時康。"]},{"t":"奉和送金城公主適西蕃應制","f":"other","p":["帝子今何去？重姻適異方。","離情愴宸掖，別路遶關梁。","望絕園中柳，悲纏陌上桑。","空餘願黃鶴，東顧憶迴翔。"]},{"t":"餞許州宋司馬赴任","f":"other","p":["潁川開郡邑，角宿分躔野。","君非仲舉才，誰是題輿者。","憫憫琴上鶴，蕭蕭路傍馬。","嚴程若可留，別袂希再把。"]},{"t":"餞唐州高使君赴任","f":"other","p":["外牧資賢守，斯人奉帝俞。","淮南膺建隼，渭北暫分符。","坐歎煙波隔，行嗟物候殊。","何年昇美課，迴首北城隅。"]},{"t":"奉和立春遊苑迎春應制","f":"other","p":["玄籥飛灰出洞房，青郊迎氣肇初陽。","仙輿暫下宜春苑，御醴行開薦壽觴。","映水輕苔猶隱綠，緣堤弱柳未舒黃。","唯有裁花飾簪鬢，恆隨聖藻狎年光。"]},{"t":"奉和聖製春日幸望春宮應制","f":"other","p":["綵仗琱輿俯碧潯，行春御氣發皇心。","搖風細柳縈馳道，映日輕花出禁林。","遍野園亭開帟幕，連堤草樹狎衣簪。","謬參西掖霑堯酒，願沐南薰解舜琴。"]},{"t":"奉和人日讌大明宮恩賜綵縷人勝應制","f":"other","p":["日宇千門平旦開，天容萬象列昭回。","三陽候節金爲勝，百福迎祥玉作杯。","就暖風光偏著柳，辭寒雪影半藏梅。","何幸得參詞賦職，自憐終乏馬卿才。"]},{"t":"奉和幸安樂公主山莊應制","f":"other","p":["主家臺沼勝平陽，帝幸歡娛樂未央。","掩映琱窗交極浦，參差繡戶繞迴塘。","泉聲百處傳歌曲，樹影千重對舞行。","聖酒一霑何以報，唯欣頌德奉時康。"]},{"t":"興慶池侍宴應制","f":"other","p":["積水逶迤繞直城，[含]虛皎鏡有餘清。","圖雲曲榭連緹幕，映日中塘間綵旌。","賞洽猶聞簫管沸，歡留更睹木蘭輕。","無勞海上尋仙客，即此蓬萊在帝京。"]},{"t":"夜宴安樂公主宅","f":"other","p":["鳳樓䆗窱凌三襲，翠幌玲瓏瞰九衢。","複道中宵留宴衎，彌令上客想踟躕。"]},{"t":"餞唐永昌","f":"other","p":["聞君出宰洛陽隅，賓友稱觴餞路衢。","別後相思在何處？祗應關下望仙鳧。"]}],"cp-5cd7072a":[{"t":"奉和九日幸臨渭亭登高應制得明字","f":"other","p":["鑾輿巡上苑，鳳駕瞰層城。","御座丹烏麗，宸居白鶴驚。","玉旗縈桂葉，金杯汎菊英。","九晨陪聖膳，萬歲奉承明。"]}],"cp-5d8446ca":[{"t":"湘靈鼓瑟","f":"other","p":["瑤瑟多哀怨，朱弦且莫聽。","扁舟三楚客，藂竹二妃靈。","淅瀝聞餘響，依稀欲辨形。","柱間寒水碧，曲裏暮山青。","良馬悲銜草，遊魚思繞萍。","知音若相遇，終不滯南溟。"]}],"cp-d5ce6893":[{"t":"自悼","f":"other","p":["朝日上團團，照見先生盤。","盤中何所有，苜蓿長闌干。","飯澁匙難綰，羹稀筯易寬。","只可謀朝夕，何由保歲寒。"]},{"t":"靈巖寺","f":"other","p":["草堂棲在靈山谷，勤苦詩書向燈燭。","柴門半掩寂無人，惟有白雲相伴宿。"]},{"t":"太姥山","f":"other","p":["揚舲窮海島，選勝訪神仙。","鬼斧巧開鑿，仙蹤常往還。","東甌冥漠外，南越渺茫間。","爲問容成子，刀圭乞駐顏。","（《古今圖書集成·職方典》一一○八《福寧州部》）。"]},{"t":"草堂吟","f":"other","p":["草堂棲在靈山谷，勤讀詩書向燈燭。","柴門半掩寂無人，惟有白雲相伴宿。","春日溪頭垂釣歸，花笑鶯啼芳草綠。","猿鶴寥寥愁轉深，携琴獨理仙家曲。","曲中哀怨誰知妙，子期能識宮商調。","魚未成龍劍未飛，家貧耽學人爭笑。","君不見蘇秦與韓信，獨步誰知是英俊。","一朝得遇聖明君，腰間各佩黃金印。","男兒立志需稽古，莫厭燈前讀書苦。","自古公侯未遇時，蕭條長閉山中戶。","（見《高岑三廉薛氏宗譜》，轉錄自《唐代文學論叢》第九期刊施景西《薛令之的〈靈巖寺〉詩及其寫作時代》）（按：《全唐詩》卷二一五僅收此詩之首四句，題作《靈巖寺》。","據施景西考，《靈巖寺》詩題爲咸通元年後的輯錄者所加。","）。"]}],"cp-2932ac77":[{"t":"和張相公太原山亭懷古詩","f":"other","p":["公府政多暇，思與仁智全。","爲山想巖穴，引水聽潺湲。","軒冕迹自逸，塵俗無由牽。","蒼生方矚望，詎得賦歸田。"]}],"cp-209ab1a2":[{"t":"夜吟","f":"other","p":["秋逕填黃葉，寒摧露草根。","猨聲一叫斷，客淚數重痕。"]}],"cp-dd3f43c6":[{"t":"夢中歌","f":"other","p":["今夕何夕，存耶沒耶。","良人去兮天之涯，園樹傷心兮三見花。"]}],"cp-f88f7c42":[{"t":"爲溫僕射嘲竹","f":"other","p":["竹，風吹青肅肅，凌冬葉不凋，經春子不熟。","虚心未得待國士，皮上何湏生節目。"]},{"t":"又嘲屏牆","f":"other","p":["高下八九尺，東西六七步。","突兀當廳坐，幾許遮賢路。"]}],"cp-d91347f8":[{"t":"嘲郭凝素","f":"other","p":["三春桃李本無言，苦被殘陽鳥雀喧。","借問東鄰效西子，何如郭素擬王軒。"]}],"cp-bec86b8d":[{"t":"句","f":"other","p":["良宰多憂憫，虔誠謁庶神。","（〖1〗句次趙不爲祈雨詩句後，曰「七𠥱〖月〗廿三〖乙〗〖日〗，文林郎王堅詩曰〖句不重錄〗」云云。","）。"]}],"cp-864949bd":[{"t":"歌","f":"other","p":["黑白兩迴開佛眼，不繫一法出蓮叢。","真空不壞靈智性，妙用恒常無作功。","聖智本來成佛道，寂光非照自圓通。","（見《大正新修大藏經》第四十八冊吳越釋延壽《宗鏡錄》卷十八）。"]}],"cp-de8ae41e":[{"t":"送最澄上人還日本國","f":"other","p":["家與扶桑近，煙波望不窮。","來求貝葉偈，遠過海龍宮。","流水隨歸處，征帆遠向東。","相思渺無畔，應使夢魂通。","（同前）。"]}],"cp-dc8115fe":[{"t":"頌 一","f":"other","p":["風動心搖樹，雲生性起塵。","若明今日事，昧却本來人。"]},{"t":"頌 二","f":"other","p":["欲識解脫道，諸法不相到。","眼耳絕見聞，聲色鬧浩浩。"]},{"t":"頌 三","f":"other","p":["初心未入道，不得鬧浩浩。","鐘聲裏薦取，鼓聲裏顛倒。"]},{"t":"頌 諸佛不出世，四十九年說。祖師不西來，少林有妙訣。","f":"other","p":["萬法是心光，諸緣唯性曉。","本無迷悟人，秪要今日了。","（見《五燈會元》卷八。","）。"]},{"t":"頌 六","f":"other","p":["卷簾除却障，閉戶生窒礙。","祗這障與礙，古今無人會。","會得是障礙，不會不自在。","（同上。","）。"]}],"cp-764a0a35":[{"t":"自製詞","f":"other","p":["畫羅衫子畫羅裙，能結束，稱腰身。","柳眉桃臉不勝春。","薄媚足精神。","可惜許，流落在風塵。","（見《分門古今類事》卷十三《該聞錄》引。","）（按：《全唐詩》卷八八九收此詞，題作《甘州曲》，無首句前四字。","第六句無「許」字，遂與下連作七字句。","今重錄之。","）（《該聞錄》，宋初李畋作。","）。"]},{"t":"曲子","f":"other","p":["盡是（《五代詩話》引作「贏得」）一場傀儡。","（《類說》卷四三引《北夢瑣言》。","）。"]}],"cp-af0d707f":[{"t":"折红梅","f":"other","p":["喜冰澌初泮，微和渐入、东郊时节。","春消息，夜来顿觉，红梅数枝争发。","玉溪仙馆，不是个、寻常标格。","化工别与、一种风情，似匀点胭脂，染成香雪。","重吟细阅。","比繁杏夭桃，品格真别。","只愁共、彩云易散，冷落谢池风月。","凭谁向说。","三弄处、龙吟休咽。","大家留取，时倚阑干，闻有花堪折，劝君须折。"]}],"cp-bd14cbd2":[{"t":"调啸・调笑令","f":"other","p":["渔父。","渔父。","水上微风细雨。","青蓑黄箬裳衣。","红酒白鱼暮归。","暮归、暮归、归暮。","长笛一声何处。"]},{"t":"调啸・调笑令","f":"other","p":["归雁。","归雁。","饮啄江南南岸。","将飞却下盘桓。","塞北春来苦寒。","苦寒。","苦寒。","寒苦。","藻荇欲生且住。"]},{"t":"水调歌头","f":"other","p":["离别一何久，七度过中秋。","去年东武今夕，明月不胜愁。","岂意彭城山下，同泛清河古汴，船上载凉州。","鼓吹助清赏，鸿雁起汀洲。","坐中客，翠羽帔，紫绮裘。","素娥无赖，西去曾不为人留。","今夜清尊对客，明夜孤帆水驿，依旧照离忧。","但恐同王粲，相对永登楼。"]},{"t":"渔家傲","f":"other","p":["七十馀年真一梦。","朝来寿斝儿孙奉。","忧患已空无复痛。","心不动。","此间自有千钧重。","早岁文章供世用。","中年禅味疑天纵。","石塔成时无一缝。","谁与共。","人间天上随他送。"]}],"cp-1e753f82":[{"t":"念奴娇","f":"other","p":["扁舟夜泛，向子陵台下，偃帆收橹。","水阔风摇舟不定。","依约月华新吐。","细酌清泉，痛浇尘臆，唤起先生语。","当年纶钓，为谁高卧烟渚。","还念古往今来，功名可共，能几人光武。","一旦星文惊四海，从此故人何许。","到底轩裳，不如蓑笠，久矣心相与。","天低云淡，浩然吾欲高举。"]}],"cp-a114f575":[{"t":"蓦山溪","f":"other","p":["芳菲叶底。","谁会秋江意。","深绿护轻黄，怕青女、霜侵憔悴。","开分早晚，都占九秋天，花四出，香七里。","独步珠宫里。","佳名岩桂。","却是因遗子。","不自月中来，又那得、萧萧风味。","霓裳旧曲，休问广寒人，飞太白，酬仙蕊。","香外无香比。"]},{"t":"临江仙","f":"other","p":["寒甚正前三五日。","风将腊雪侵寅。","彩鸡缕燕已惊春。","玉梅飞上苑，金柳动天津。","□□□□□□□，□□□□□□。","□□□□□□□。","春盘共饤饾，绕坐庆时新。"]},{"t":"雪明鹊夜慢・雪明鹊夜","f":"other","p":["望五云多处春深，开阆苑、别就蓬岛。","正梅雪韵清，桂月光皎。","凤帐龙帘萦嫩风，御座深、翠金间绕。","半天中、香泛千花，灯挂百宝。","圣时观风重腊，有箫鼓沸空，锦绣匝道。","竞呼卢、气贯调欢笑。","暗里金钱掷下，来侍燕、歌太平睿藻。","愿年年此际，迎春不老。"]},{"t":"凤皇枝令・凤凰枝令","f":"other","p":["人间天上。","端楼龙凤灯先赏。","倾城粉黛月明中，春思荡。","醉金瓯仙酿。","一从鸾辂北向。","旧时宝座应蛛网。","游人此际客江乡，空怅望。","梦连昌清唱。"]},{"t":"南歌子","f":"other","p":["梅夏暗丝雨，麦秋扇浪风。","香芦结黍趁天中。","五日凄凉今古、与谁同。"]},{"t":"明月照高楼慢・明月照高楼","f":"other","p":["平分素商。","四垂翠幕，斜界银潢。","颢气通建章。","正烟澄练色，露洗水光。","明映波融太液，影随帘挂披香。","楼观壮丽，附霁云、耀绀碧相望。","宫妆。","三千从赭黄。","万年世代，一部笙簧。","夜宴花漏长。","乍莺歌断续，燕舞回翔。","玉座频燃绛蜡，素娥重按霓裳。","还是共唱御制词，送御觞。"]},{"t":"失调名","f":"other","p":["昔年曾共黄花酒，一笑新香。"]},{"t":"尉迟杯慢・尉迟杯","f":"other","p":["碎云薄。","向碧玉枝缀万萼。","如将汞粉匀开，疑使柏麝熏却。","雪魄未应若。","况天赋、标艳仍绰约。","当暄风暖日佳处，戏蝶游蜂看著。","重重绣帘珠箔。","障秾艳霏霏，异香漠漠。","见说徐妃，当年嫁了，信任玉钿零落。","无言自啼露萧索。","夜深待、月上栏干角。","广寒宫、要与姮娥，素妆一夜相学。"]},{"t":"钿带长中腔","f":"other","p":["簇真香。","似风前拆麝囊。","嫩紫轻红，间斗异芳。","风流富贵，自觉兰蕙荒。","独占蕊珠春光。","绣结流苏密织，魂梦悠扬。","气融液散满洞房。","朝寒料峭，殢娇不易当。","著意要得韩郎。"]},{"t":"春草碧・番枪子","f":"other","p":["又随芳绪生，看翠霁连空，愁遍征路。","东风里，谁望断西塞，恨迷南浦。","天涯地角，意不尽、消沈万古。","曾是送别长亭下，细绿暗烟雨。","何处。","乱红铺绣茵，有醉眠荡子，拾翠游女。","王孙远，柳外共残照，断云无语。","池塘梦生，谢公后、还能继否。","独上画楼，春山暝、雁飞去。"]},{"t":"三台","f":"other","p":["见梨花初带夜月，海棠半含朝雨。","内苑春、不禁过青门，御沟涨、潜通南浦。","东风静、细柳垂金缕。","望凤阙、非烟非雾。","好时代、朝野多欢，遍九陌、太平箫鼓。","乍莺儿百啭断续，燕子飞来飞去。","近绿水、台榭映秋千，斗草聚、双双游女。","饧香更、酒冷踏青路。","会暗识、夭桃朱户。","向晚骤、宝马雕鞍，醉襟惹、乱花飞絮。","正轻寒轻暖漏永，半阴半晴云暮。","禁火天、已是试新妆，岁华到、三分佳处。","清明看、汉宫传蜡炬。","散翠烟、飞入槐府。","敛兵卫、阊阖门开，住传宣、又还休务。"]},{"t":"恋芳春慢","f":"other","p":["蜂蕊分香，燕泥破润，暂寒天气清新。","帝里繁华，昨夜细雨初匀。","万品花藏四苑，望一带、柳接重津。","寒食近，蹴踘秋千，又是无限游人。","红妆趁戏，绮罗夹道，青帘卖酒，台榭侵云。","处处笙歌，不负治世良辰。","共见西城路好，翠华定、将出岩宸。","谁知道，仁主祈祥为民，非事行春。"]},{"t":"安平乐慢","f":"other","p":["瑞日初迟，绪风乍暖，千花百草争香。","瑶池路稳，阆苑春深，云树水殿相望。","柳曲沙平，看尘随青盖，絮惹红妆。","卖酒绿阴傍。","无人不醉春光。","有十里笙歌，万家罗绮，身世疑在仙乡。","行乐知无禁，五侯半隐少年场。","舞妙歌妍，空妒得、莺娇燕忙。","念芳菲、都来几日，不堪风雨疏狂。"]},{"t":"卓牌儿・卓牌子","f":"other","p":["东风绿杨天，如画出、清明院宇。","玉艳淡泊，梨花带月，胭脂零落，海棠经雨。","单衣怯黄昏，人正在、珠帘笑语。","相并戏蹴秋千，共携手、同倚栏干，暗香时度。","翠窗绣户。","路缭绕、潜通幽处。","断魂凝伫。","嗟不似飞絮。","闲闷闲愁，难消遣、此日年年意绪。","无据。","奈酒醒春去。"]},{"t":"昭君怨","f":"other","p":["春到南楼雪尽。","惊动灯期花信。","小雨一番寒。","倚阑干。","莫把阑干倚。","一望几重烟水。","何处是京华。","暮云遮。"]},{"t":"昭君怨","f":"other","p":["一望西山烟雨。","目断心飞何处。","天外白云城。","几多程。","谩记阳关句。","衣上粉啼痕污。","陇水一分流。","此生休。"]},{"t":"诉衷情","f":"other","p":["一鞭清晓喜还家。","宿醉困流霞。","夜来小雨新霁，双燕舞风斜。","山不尽，水无涯。","望中赊。","送春滋味，念远情怀，分付杨花。"]},{"t":"梅花引","f":"other","p":["晓风酸。","晓霜乾。","一雁南飞人度关。","客衣单。","客衣单。","千里断魂，空歌行路难。","寒梅惊破前村雪。","寒鸡啼破西楼月。","酒肠宽。","酒肠宽。","家在日边，不堪频倚阑。"]},{"t":"忆秦娥","f":"other","p":["千里草。","萋萋尽处遥山小。","遥山小。","行有远似，此山多少。","天若有情天亦老。","此情说便说不了。","说不了。","一声唤起，又惊春晓。"]},{"t":"忆少年","f":"other","p":["陇云溶泄，陇山峻秀，陇泉呜咽。","行人暂驻马，已不胜愁绝。","上陇首、凝眸天四阔。","更一声、塞雁凄切。","征书待寄远，有知心明月。"]},{"t":"长相思","f":"other","p":["一声声。","一更更。","窗外芭蕉窗里灯。","此时无限情。","梦难成。","恨难平。","不道愁人不喜听。","空阶滴到明。"]},{"t":"长相思","f":"other","p":["短长亭。","古今情。","楼外凉蟾一晕生。","雨馀秋更清。","暮云平。","暮山横。","几叶秋声和雁声。","行人不要听。"]},{"t":"木兰花慢","f":"other","p":["恨莺花渐老，但芳草、绿汀洲。","纵岫壁千寻，榆钱万叠，难买春留。","梅花向来始别，又匆匆，结子满枝头。","门外垂杨岸侧，画桥谁系兰舟。","悠悠。","岁月如流。","叹水覆、杳难收。","凭画阑，往往抬头举眼，都是春愁。","东风晚来更恶，怕飞红、拍絮入书楼。","双燕归来问我，怎生不上帘钩。"]},{"t":"武陵春","f":"other","p":["燕子飞来花在否，微雨退、掩重门。","正满院梨花雪照人。","独自个、怯黄昏。","轻风淡月总消魂。","罗衣暗惹啼痕。","谩觑著、秋千腰褪裙。","可㬠是、不宜春。"]},{"t":"快活年近拍","f":"other","p":["千秋万岁君，五帝三王世。","观风重令节，与民乐盛际。","蕊宫长春，洞天不老，花艳蝉辉，十里照春珠翠。","闹罗绮。","遥望太极，一簇通明里。","钧台奏寿，蓬山呈妙戏。","六宫人来，五云楼迥，风送歌声，依约睿思圣制。"]},{"t":"醉蓬莱","f":"other","p":["正波泛银汉，漏滴铜壶，上元佳致。","绛烛银灯，若繁星连缀。","明月逐人，暗尘随马，尽五陵豪贵。","鬓惹乌云，裙拖湘水，谁家姝丽。","金阙南边，彩山北面，接地罗绮，沸天歌吹。","六曲屏开，拥三千珠翠。","帝乐□深，凤炉烟喷，望舜颜瞻礼。","太平无事，君臣宴乐，黎民欢醉。"]},{"t":"芰荷香","f":"other","p":["小潇湘。","正天影倒碧，波面容光。","水仙朝罢，间列绿盖红幢。","吹风细雨，荡十顷、浥浥清香。","人在水精中央。","霜绡雾縠，襟袂收凉。","款放轻舟闹红里，有晴蜓点水，交颈鸳鸯。","翠阴密处，曾觅相并青房。","晚霞散绮，泛远净、一叶鸣榔。","拟去尽促雕觞。","歌云未断，月上飞梁。"]},{"t":"别瑶姬慢・忆瑶姬","f":"other","p":["可惜香红。","又一番骤雨，几阵狂风。","霎时留不往，便夜来和月，飞过帘栊。","离愁未了，酒病相仍，便堪此恨中。","片片随、流水斜阳去，各自西东。","又还是、九十春光，误双飞蝶，并采游峰。","人生能几许，细算来何物，得似情浓。","沈腰暗减，潘鬓先秋，寸心不易供。","望暮云、千里沈沈障翠峰。"]},{"t":"忆秦娥","f":"other","p":["天如洗。","金波冷浸冰壶里。","冰壶里。","一年得似，此宵能几。","等闲莫把栏干倚。","马蹄去便三千里。","三千里。","几重云岫，几重烟水。"]}],"cp-5ce29778":[{"t":"极相思","f":"other","p":["日红疏翠密晴暄。","初夏困人天。","风流滋味，伤怀尽在，花下风前。","后约已知君定，这心绪、尽日悬悬。","鸳鸯两处，清宵最苦，月甚先圆。"]}],"cp-c1334a24":[{"t":"玉蝴蝶","f":"other","p":["忆昨苕溪，惯弄五亭月笛，四水烟蓑。","何事毗檀门外，马驻长坡。","野花中、乱红杳霭，小桥外、叠翠嵯峨。","且颜酡。","但存长袖，舞倒婆娑。","云何。","主盟惠政，春行五马，月皎千波。","赢得宾僚，听隔墙、无事高歌。","帐烟寒、瑞麟影坠，帘雾细、宝鸭香多。","试蹉跎。","一枰落日，又送焦柯。"]},{"t":"念奴娇","f":"other","p":["冯夷微怒，被鲛人水府，织成绡縠。","何处飞来双白鹭，点破一溪寒玉。","岸柳烟迷，海棠酒困，赢得春眠足。","凭栏搔首，为谁消遣愁目。","遥想居士床头，竹渠新雨，溜瓮中春醁。","不惜千锺为客寿，倒卧南山新绿。","晚月催归，春风留住，费尽纱笼烛。","恍疑仙洞，梦游天柱林屋。"]},{"t":"念奴娇","f":"other","p":["阳关西路，看垂阳客舍，嫩浮波縠。","宝马嘶风人渐远，隐隐歌声戛玉。","踏遍春山，归来高卧，笑濯沧浪足。","孤鸿天际，断霞摇曳心目。","香露飞入壶中，仙家九酝，酿百家醽醁。","一朵巫阳休怅望，且看家山眉绿。","歌罢风生，舞馀花颤，凤髓飘红烛。","瑶台月冷，夜归斗挂银屋。"]},{"t":"洞仙歌","f":"other","p":["璚楼十二，无限神仙侣。","紫绂丹麾彩鸾驭。","步虚声杳霭，碧落天高，微云淡，点破瑶阶白露。","暗香来水阁，冰簟纱厨，一枕风轻自无暑。","更上水精帘，斗挂阑干，银河浅、天孙将渡。","终不如、归去在苕川，看千顷菰蒲，乱鸣秋雨。"]},{"t":"洞仙歌","f":"other","p":["藐姑仙子，天外谁为侣。","八极浮游气为驭。","看朝餐沆瀣，暮饮醍醐，瑶台冷，吹落九天风露。","翠空云幕净，宝鉴无尘，碧树秋来暗消暑。","残夜水明楼，影落寒溪，行人起、沙头唤渡。","任角声、吹落小梅花，梦不到渔翁，一蓑烟雨。"]},{"t":"满庭霜・满庭芳","f":"other","p":["红叶飞时，青山缺处，云横秋影斜阳。","凤凰旌节，何事到吾乡。","要见大江东去，寒光静、水与天长。","人争看，恩袍焕锦，新惹御炉香。","满城，夸盛事，两邦鼓吹，几部笙簧。","看万红千翠，簇拥云裳。","况是重阳近也，萸露紫、菊吐轻黄。","休辞醉，明朝一枕，歌韵尚悠扬。"]},{"t":"满庭霜・满庭芳","f":"other","p":["归去来兮，苕溪深处，上有苍翠千峰。","月桥烟墅，家在五湖东。","试觅桃花流水，鸡犬静、人迹才通。","沙汀晚，一天云锦，飞下水精宫。","两年，官事少，江梅雾暗，多稼云丰。","把毗坛清梦，尽入诗筒。","只欠芦花夜宿，金溪上、一苇秋风。","蓑衣在，不辞重整，来作钓鱼翁。"]},{"t":"满庭霜・满庭芳","f":"other","p":["归去来兮，家林不远，梦魂飞绕烟峰。","洞房花木，只在小池东。","谁道云深无路，小桥外、一径相通。","功名小，从教群蚁，鏖战大槐宫。","故人，书夜到，秫田百亩，已兆年丰。","把乌程烂醉，不数郫筒。","醉后村歌社舞，团圞坐、一笑春风。","洪崖伴，定驱鸾鹤，时一访衰翁。"]},{"t":"满庭霜・满庭芳","f":"other","p":["归去来兮，心空无物，乱山不斗眉峰。","夜禅久坐，窗晓日升东。","已绝乘槎忘想，沧溪迥、不与河通。","维摩室，从教花雨，飞舞下天空。","何人，开宴豆，楚羹莼嫩，吴脍盘丰。","看一声欸乃，落日收筒。","应笑红尘陌上，津亭暮、十里斜风。","从今去，青鞋黄帽，分付紫髯翁。"]},{"t":"满江红","f":"other","p":["家住苕西，小池映、青山一曲。","翠深里、猿呼鹤应，短墙低屋。","麦影离离翻翠浪，泉声НН敲寒玉。","怪夜来、有蚁出糟床，篘新绿。","和月种，南阳菊。","饶云买，淇园竹。","任蛮争触战，世间荣辱。","两目未消凭远恨，一筇费尽登山足。","便棹舟、炊火荻花中，鲈鱼熟。"]},{"t":"满江红","f":"other","p":["卷尽珠帘，楚天迥、阑干几曲。","最好是、瑶台归路，月翻银屋。","深院数枰风入座，高楼一喷云横玉。","看橘林、霜浅未全黄，犹悬绿。","悠然意，渊明菊。","真如指，国师竹。","者是非识破，都无荣辱。","不管浮生如蝶梦，从教万事添蛇足。","坐西崑、一笑八千秋，蟠桃熟。"]},{"t":"满江红","f":"other","p":["郢客高歌，犹未睹、阳春一曲。","多应是、连城有价，閟藏华屋。","但使章台无异意，何妨一见邯郸玉。","料锦囊、随客泛东溪，凌波绿。","难独唱，篱边菊。","谁与咏，阶前竹。","想秋光不久，又成虚辱。","过雁不知蛩有恨，行夔应笑蚿无足。","愿为予、落笔走盘珠，争圆熟。"]},{"t":"念奴娇","f":"other","p":["年来衰懒，渐无心赏遍，目前佳趣。","寂寂墙阴春荠老，不到先生鼎俎。","诗卷寻医，禅林结局，酒入昏田务。","山头云气，为谁来往朝暮。","犹有筇杖多情，扪萝踏石，堕半岩花雨。","更向葭业摇短艇，惊起飞鸿烟渚。","横玉凄清，焦桐古淡，一笑忘千虑。","更阑人静，此声今在何处。"]},{"t":"念奴娇","f":"other","p":["蓬莱一岛，卧长烟千柳，西溪幽趣。","苜蓿盘中初日上，不把胾臑充俎，和月栽松，饶云买石，只此为家务。","倚楹清啸，断霞斜倚天暮。","闻道块磊浇胸，槎丫肝肺，动笔端风雨。","壁上潇湘秋一帧，影落荻花洲渚。","暗浦潮生，寒矶雪化，无复风尘虑。","此时渔父，短蓑合在何处。"]},{"t":"江神子・江城子","f":"other","p":["亭亭鹤羽戏芝田。","看群仙。","起青涟。","绿盖红幢，千乘去朝天。","留得瑶姬清夜舞，人与月，斗婵娟。","凭阑有恨不堪言。","倩谁传。","曲声圆。","写尽清愁，香弄晚风妍。","不羡山头窥井玉，花十丈，藕如船。"]},{"t":"江神子・江城子","f":"other","p":["粼粼白水护青田。","想真仙。","弄清莲。","十里香风，吹下碧云天。","月在草堂人未寝，松竹暗，水涓涓。","夜阑何事悄无言。","怨空传。","事难圆。","欲借寒光，谁与伴清妍。","待得凌波人肯住，呼玉笛，劝金船。"]},{"t":"鹧鸪天","f":"other","p":["千树家园锁旧津。","谁移数点在孤村。","海仙探蕊禽留影，楚客穿花蝶舞魂。","桥断港，水横门。","残霞零落晚烟昏。","只因留住三更月，暗里香来别是春。"]},{"t":"鹧鸪天","f":"other","p":["万木家园雾暗津。","不须踏影下前村。","须知苕霅水云窟，自有罗浮冰雪魂。","横水馆，倚楼门。","参旗有约共黄昏。","此中有句无人见，谁在樽前领略春。"]},{"t":"洞仙歌","f":"other","p":["风摇丹髻，叶翦西岩树。","岁律峥嵘又如许。","看千峰倒影，浮动觥船，纱窗外，万幅鲛绡斗舞。","五弦弹不尽，碧落天高，隐隐孤鸿向云度。","送斜红敛尽，催上蟾钩，金风细，点破瑶阶白露。","任笛声、吹残一帘秋，看人□栏□，暮云高处。"]},{"t":"洞仙歌","f":"other","p":["橹声伊轧，影转云间树。","试问扁舟在何许。","正溪堂波动，沙渚苹轻，渔翁醉，隔岸蓑衣对舞。","归来无一事，尊酒相逢，莫把光阴更虚度。","看歌云杳霭，香雾轻盈，银河转，笑浥芙蓉晓露。","纵西风、黄叶满庭秋，也不碍凝眸，乱山多处。"]},{"t":"洞仙歌","f":"other","p":["丹青明灭，霜著谁家树。","满眼风光向谁许。","送寒鸦万点，流水孤村，归来晚，月影三人夜舞。","金英秋已老，蜡缀寒葩，空里时闻暗香度。","任一枝瓶小，数点钗寒，佳人笑，饮尽床头玉露。","看纱窗、红日上三竿，把蝶影捎空，在花深处。"]},{"t":"水调歌头","f":"other","p":["年来惯行役，楚尾又吴头。","餐霞吸露，何事佳处辄迟留。","云听渔舟夜唱，花落牧童横笛，占尽五湖秋。","胡床兴不浅，人在庾公楼。","绣帘卷，曲阑暝，翠鬟愁。","森罗万象，与渠诗里一时收。","天设四桥风月，地会三州山水，邀我伴沙鸥。","明朝起归梦，一枕过苹洲。"]},{"t":"水调歌头","f":"other","p":["帆腹饱天际，树发渺云头。","翠光千顷，为谁来去为谁留。","疑是吴宫西子，淡扫修眉一抹，妆罢玉奁秋。","中流送行客，却立望层楼。","风色变，堤草乱，浪花愁。","跳珠翻墨，轰雷掣电几时收。","应是阳侯薄相，催我胸中锦绣，清唱和鸣鸥。","残霞似相贷，一缕媚汀洲。"]},{"t":"水调歌头","f":"other","p":["青铜昏水面，乌帽裹山头。","风涛如此，天公作意巧相留。","常记垂虹晚渡，卧看菰蒲烟雨，屈指十三秋。","恍若华胥梦，无语下西楼。","翠翻空，寒入座，不禁愁。","五弦弹尽，隐隐天末暮虹收。","欲伴渔翁钓艇，欸乃一声江上，寒碧点轻鸥。","无人阻归兴，直欲迈长洲。"]},{"t":"兰陵王","f":"other","p":["乱烟簇。","帘外青山渐肃。","莲房静。","荷盖半残，欲放清涟媚溪绿。","凭高送远目。","飞起沧洲雁骛。","寒窗静，茶碗未深，一枕胡床画眠足。","闲行问松菊。","今□雨谁家，空对银烛。","箫声忽下瑶台曲。","看鹤舞风动，乌啼云起，何须舟内怨女哭。","抱琴写幽独。","情触。","会相续。","况节近中元，月浪翻屋。","长鲸愁晓寒蟾促。","要百柁倾□，万花流玉。","山肴倒尽，又空腹，鲙野蔌。"]},{"t":"柳梢青","f":"other","p":["谢家池阁。","翠桁香浓，琐纱窗薄。","夜雨灯前，秋风笔下，与谁同乐。","主人许我清狂，奈酒量、从来最弱。","颠倒冠巾，淋漓衣袂，醒时方觉。"]},{"t":"柳梢青","f":"other","p":["空中雨阁。","一段轻阴，翠铺林薄。","橘内仙翁，棋边公子，共成清乐。","主人有井留车，看席上、云轻柳弱。","斗转檐头，鸡鸣窗外，无人知觉。"]},{"t":"朝中措","f":"other","p":["双鞬锦领出山西。","戎幕护旌旗。","横槊春风百咏，临淮夜月千卮。","风流樽俎，琼花破艳，红药攒枝。","赏尽竹西歌吹，珠帘十里香迷。"]},{"t":"感皇恩","f":"other","p":["风雨半摧残，一园花老。","绿遍池塘夜来草。","看花何处，莫被此花相恼。","世间多少事，邯郸道。","凭远下临，暗尘飞绕。","数点烟中树、水村小。","斜阳且住，为我花间留照。","从教红满地，何须扫。"]},{"t":"感皇恩","f":"other","p":["花似镜中人，不堪衰老。","空羡青青岸边草。","多情消瘦，更被无情相恼。","近来无限事，凭谁道。","胡蝶满园，丛边空绕。","睡起流莺过、语声小。","琐窗危坐，更被玉蟾相照。","夜阑梅影瘦，凭谁扫。"]}],"cp-091bbd81":[{"t":"水调歌头","f":"other","p":["寒眼乱空阔，客意不胜秋。","强呼斗酒，发兴特上最高楼。","舒卷江山图画，应答龙鱼悲啸，不暇顾诗愁。","风露巧欺客，分冷入衣裘。","忽醒然，成感慨，望神州。","可怜报国无路，空白一分头。","都把平生意气，只作如今憔悴，岁晚若为谋。","此意仗江月，分付与沙鸥。"]},{"t":"水调歌头","f":"other","p":["杖屦觅春色，行遍大江西。","访花问柳，都自无语欲成蹊。","不道七州三垒，今岁五风十雨，全是太平时。","征辔晚乘月，渔钓夜垂丝。","诗书帅，坐围玉，尘挥犀。","兴方不浅，领袖风月过花期。","只恐梅梢青子，已露调羹消息，金鼎待公归。","回首腾王阁，空对落霞飞。"]},{"t":"水调歌头","f":"other","p":["父老一杯酒，争劝史君留。","可怜桃李千树，无语送归舟。","听得拈笙玉指，都把万家遗爱，吹作许离愁。","倚醉袖红湿，生怕夕阳流。","问君侯，今几日，到东州。","还家时候，次第梅已暗香浮。","只恐道间驿使，先寄调羹消息，归去总无由。","鼎铉功名了，徐赴赤松游。"]},{"t":"水调歌头","f":"other","p":["买得一航月，醉卧出长安。","平堤千里过尽，杨柳绿阴间。","依约晓莺啼处，认得南徐风物，客梦恍惊残。","重到旧游所，如把画图看。","英雄事，千古意，一凭阑。","惜今老矣，无复健笔写江山。","天上人间知己，赖有使星郎宿，照映此尘寰。","准拟五湖去，为乞钓鱼竿。"]},{"t":"水调歌头","f":"other","p":["把酒对斜阳，无语问西风。","胭脂何事，都做颜色染芙蓉。","放眼暮江千顷，中有离情万斛，无处落征鸿。","天在阑干角，人倚醉醒中。","千万里，江南北，浙西东。","吾生如寄，尚想三径菊花丛。","谁是中州豪杰，借我五湖舟楫，去作钓渔翁。","故园且回首，此意莫匆匆。"]},{"t":"水调歌头","f":"other","p":["一笛起城角，吹破小梅愁。","东风犹未，谁遣春信到吾州。","闻得东来千骑，鼓舞儿童竹马，和气与空浮。","桃李未阴处，准拟种千头。","今太守，宋人物，晋风流。","政成谈笑，不妨高兴在南楼。","只恐蓬莱仙伯，合侍玉皇香案，难作寇恂留。","约住紫泥诏，凭轼且优游。"]},{"t":"水调歌头","f":"other","p":["踏碎九街月，乘醉出京华。","半生湖海，谁念今日老还家。","独把瓦盆盛酒，自与渔樵分席，说伊政声佳。","竹马望尘去，倦客亦随车。","听熏风，清晓月，韵梅花。","人家十万，说尽炎热与咨嗟。","只恐棠阴未满，已有枫宸趣召，归路不容遮。","回首江边柳，空著旧栖鸦。"]},{"t":"满江红","f":"other","p":["春入台门，又见染、柳丝新绿。","对此景，一年为寿，一番添福。","莫怪凤池颁诏晚，要教淮水恩波足。","听边民、千岁颂声中，重重祝。","堂萱茂，庭枝馥。","歌倚扇，杯持玉。","共劝君一醉，满斟醽醁。","今夜东风吹酒醒，明朝万里骑黄鹄。","向九霞、光里望宸辉，看除目。"]},{"t":"满江红","f":"other","p":["笔染相思，暗题尽、朱门白壁。","动离思、春生远岸，烟销残日。","杨柳结成罗带恨，海棠染就胭脂色。","想深情、幽怨绣屏间，双鶒鸂。","春水绿，春山碧。","花有恨，酒无力。","对一奁愁思，九分孤寂。","寸寸锦肠浑欲断，盈盈玉泪应偷滴。","倩东风、吹雁过江南，传消息。"]},{"t":"满江红","f":"other","p":["寿酒如渑，拼一醉、劝君休惜。","君不记、济河津畔，当年今夕。","万丈文章光焰里，一星飞堕从南极。","便御飞、乘兴入京华，班乡棘。","君不是，长庚白。","又不是，严陵客。","只应是，明主梦中良弼。","好把袖间经济手，如今去补天西北。","等瑶池、侍宴夜归时，骑箕翼。"]},{"t":"满江红","f":"other","p":["典尽春衣，也应是、京华倦客。","都不记，麴尘香雾，西湖南陌。","儿女别时和泪拜，牵衣曾问归时节。","到归来、稚子已成阴，空头白。","功名事，云霄隔。","英雄伴，东南拆。","对鸡豚社酒，依然乡国。","三径不成陶令隐，一区未有扬雄宅。","问渔樵、学作生生涯，从今日。"]},{"t":"瑞鹤仙","f":"other","p":["风光开旧眼。","正梅雪初消，柳丝新染。","楼台竞装点。","照金荷十里，珠帘齐卷。","湘弦楚管。","动香风、旌旗影转。","望云间，一点台星飞下，洞天清晚。","争看。","袖红围坐，舞翠回春，笑歌生暖。","欢声正远。","嬉游意，未容懒。","恐丝纶趣召，清都仙伯，归去朝天夜半。","倩邦人、挽取遨头，醉扶玉腕。"]},{"t":"贺新郎","f":"other","p":["十日狂风雨。","扫园林、红香万点，送春归去。","独有荼䕷开未到，留得一分春住。","早杨柳、趁晴飞絮。","可奈暖埃欺昼永，试薄罗衫子轻如雾。","惊旧恨，到眉宇。","东风台榭知何处。","问燕莺如今，尚有春光几许。","可欢一年游赏倦，放得无情露醑。","为唤取、扇歌裙舞。","乞得风光远两眼，待为君、满把金杯举。","扶醉玉，伴挥麈。"]},{"t":"贺新郎","f":"other","p":["梦里骖鸾驭。","望蓬莱不远，翩然被风吹去。","吹到楚楼烟月上，不记人间何处。","但疑是、蓬壶别所。","缥缈霓裳天女队，奉一仙、满把流霞举。","如唤我，醉中舞。","醉醒梦觉知何许。","问潇湘今日，谁与主盟尊俎。","无限青春难老意，拟倩管弦寄与。","待新筑沙堤稳步。","万里云霄都历遍，却依前、流水桃源路。","留此笔，为君赋。"]},{"t":"念奴娇","f":"other","p":["汉天云静，望一星飞过，湘南湘北。","当是郴山猿鹤梦，唤起日边消息。","羽扇纶巾，浩然乘兴，此意无人识。","扁舟千里，但闻清夜横笛。","记得天上人间，去年今日，曾作称觞客。","明月风烟依旧似，只觉蓬莱悬隔。","更恐明朝，诏黄飞下，趣驾冲霄翼。","衮衣剑履，望公长在南极。"]},{"t":"念奴娇","f":"other","p":["杏花杨柳，对东风染尽、一年春色。","弹压烟光三万顷，谁识清都仙伯。","夜泛银潢，手移星纬，飞堕从天阙。","御风乘兴，偶然身到乡国。","二年人乐升平，舞台歌榭，处处红牙拍。","寿酒千觞斟不尽，一醉何妨今夕。","更约明年，凤凰迟上，去作称觞客。","梅花折得，赠君调鼎消息。"]},{"t":"洞仙歌","f":"other","p":["芙蓉开了，春未江梅透。","小小东风弄晴昼。","把万家和气，吹入笙歌，炉熏里，都与慈闱做寿。","黄堂今日贵，自著莱衣，捧劝金船十分酒。","愿从今，江海上，日日韶华桃李迳，总为人间种就。","但看取、天边老人星，有一点台星，共光南斗。"]},{"t":"洞仙歌","f":"other","p":["带湖佳处，仿佛真蓬岛。","曾对金樽伴芳草。","见桃花流水，别是春风，笙歌里，谁信东君曾老。","功名都莫问，总是神仙，买断风光镇长好。","但如今，经国手，袖里偷闲，天不管、怎得关河事了。","待貌取、精神上凌烟，却旋买扁舟，归来闻早。"]},{"t":"鹊桥仙","f":"other","p":["思归时节，乍寒天气，总是离人愁绪。","夜来无奈被西风，更吹作、一帘秋雨。","征衫拂泪，阑干倚醉，羞对黄花无语。","寄书除是雁来时，又只恐、书成雁去。"]},{"t":"鹊桥仙","f":"other","p":["筑成台榭，种成花柳，更又教成歌舞。","不知谁为带湖仙，收拾尽、壶天风露。","闲中得味，酒中得趣，只恐天还也妒。","青山纵买万千重，遮不断、诏书来路。"]},{"t":"蝶恋花","f":"other","p":["离恨做成春夜雨。","添得春江，划地东流去。","弱柳系船都不住。","为君愁绝听鸣橹。","君到南徐芳草渡。","想得寻春，依旧当年路。","后夜独怜回首处。","乱山遮隔无重数。"]},{"t":"蝶恋花","f":"other","p":["点检笙歌多酿酒。","不放东风，独自迷杨柳。","院院翠阴停永昼。","曲栏随处堪垂手。","昨日解酲今夕又。","消得情怀，长被春僝僽。","门外马嘶人去后。","乱红不管花消瘦。"]},{"t":"蝶恋花","f":"other","p":["万点飞花愁似雨。","峭杀轻寒，不会留春住。","满地乱红风扫聚。","只教燕子衔将去。","独倚阑干闲自觑。","深院无人，行到无情处。","帘外丝丝杨柳舞。","又还装点人情绪。"]},{"t":"千秋岁","f":"other","p":["五云缥缈。","朝退金门晓。","归未稳，传宣到。","龙楼陪夕宴，凤沼吟春草。","人间世，谁知自有蓬莱岛。","一杯宜劝了。","换得天颜笑。","人不老，春长好。","从今千百岁，总是中书考。","瑶池会，金盘剩荐安期枣。"]},{"t":"玉人歌","f":"other","p":["风西起。","又老尽篱花，寒轻香细。","漫题红叶，句里意谁会。","长天不恨江南远，苦恨无书寄。","最相思，盘桔千枚，脍鲈十尾。","鸿雁阻归计。","算愁满离肠，十分岂止。","倦倚阑干，顾影在天际。","凌烟图画青山约，总是浮生事。","判从今，买取朝醒夕醉。"]},{"t":"点绛唇","f":"other","p":["邂逅开尊，眼中有个人纤软。","袖罗轻转。","玉腕回春暖。","韵处无多，只恼人肠断。","词将半。","近前相劝。","扑扑清香满。"]},{"t":"点绛唇","f":"other","p":["水载离怀，暮帆吹月寒欺酒。","楚梅春透。","忍放持杯手。","莫唱阳关，免湿盈盈袖。","君行后。","那人消瘦。","不恼诗肠否。"]},{"t":"秦楼月・忆秦娥","f":"other","p":["东风寂。","垂杨舞困春无力。","春无力。","落红不管，杏花狼籍。","断肠芳草萋萋碧。","新来怪底相思极。","相思极。","冷烟池馆，又将寒食。"]},{"t":"浣溪沙","f":"other","p":["杨柳笼烟袅嫩黄。","桃花蘸水染红香。","薄罗衫子日初长。","饮尽东风三百盏，醉来愁断几回肠。","教人独自遣风光。"]},{"t":"浣溪沙","f":"other","p":["三迳闲情傲落霞。","五湖高兴不浮家。","自斟北斗浸丹砂。","闲把胸中千涧壑，撰成醉处一生涯。","雪楼风月篆岗花。"]},{"t":"桃源忆故人","f":"other","p":["尊前未语眉先皱。","只把横波斜溜。","此意问春知否。","蝶困蜂儿瘦。","𦟂膎呷丁些来酒。","越会把人僝僽。","有个约伊时候。","梦里来相就。"]},{"t":"踏莎行","f":"other","p":["宿鹭栖身，飞鸿点泪，不堪更是重阳到。","一襟无处著凄凉。","倚阑堪尽斜阳倒。","瘦减难丰，悲伤易老，淡觞消得黄花笑。","画眉人去玉篦存，浓愁如黛凭谁扫。"]},{"t":"减字木兰花","f":"other","p":["月明如昼。","占断小楼供把酒。","入眼人人。","如月精神更有情。","大家休睡。","留到天明和月醉。","生怕醒来。","月到波心忆酒媒。"]},{"t":"生查子","f":"other","p":["金莲照夜红，玉腕扶春碧。","曲妙遏云行，人好欺花色。","欢生酒面浓，笑染炉香湿。","饮尽十玻璃，月堕东方白。"]},{"t":"柳梢青","f":"other","p":["生紫衫儿。","影金领子，著得偏宜。","步稳金莲，香熏纨扇，舞转花枝。","捧杯更著𦟂膎。","唱一个、新行耍词。","玉骨冰肌，好天良夜，怎不怜伊。"]},{"t":"相见欢","f":"other","p":["江湖万里征鸿。","再相逢。","多少风烟摸在、笑谈中。","歌裙醉。","罗巾泪。","别愁浓。","瘦减腰围不碍、带金重。"]},{"t":"诉衷情","f":"other","p":["露珠点点欲团霜。","分冷与纱窗。","锦书不到肠断，烟水隔茫茫。","征燕尽，塞鸿翔。","睇风樯。","阑干曲处，又是一番，倚尽斜阳。"]},{"t":"满江红","f":"other","p":["豹尾班中，谁一似、神仙冠玉。","认得是、当年唱第，斗间星宿。","万卷平生都看了，如今剗地无书读。","向云霄、去路有行堤，沙新筑。","黄封酒，生朝禄。","金缕唱，生朝曲。","且通宵一醉，剩裁红烛。","待做太平真宰相，黑头坐对三槐绿。","问恁时、犹有甚除书，长生箓。"]}],"cp-f5a4529d":[{"t":"谒金门","f":"other","p":["花过雨。","又是一番红素。","燕子归来愁不语。","故巢无觅处。","谁在玉楼歌舞。","谁在玉关辛苦。","若使边尘吹得去。","东风侯万户。"]},{"t":"齐天乐","f":"other","p":["藕花洲上芙蓉楫，羞郎故移深处。","弄影萍开，搴香袖罥，鸂鶒双双飞去。","垂鞭笑顾。","问住否横塘，试窥帘户。","妙舞妍歌，甚时相见定相许。","归来憔悴锦帐，久尘金犊幰，连娟黛眉颦妩。","扇底红铅，愁痕暗渍，消得腰支如杵。","鸾弦解语。","镇明月西南，拌人凄楚。","闷拾杨花，等闲春又负。"]}],"cp-5c6d68ad":[{"t":"晴偏好","f":"other","p":["平湖百顷生芳草。","芙蓉不照红颠倒。","东坡道。","波光潋滟晴偏好。"]}],"cp-ef747913":[{"t":"临江仙","f":"other","p":["莫怪钱神容易致，钱神尽是愚夫。","为何此鬼却相於。","只因频展义，长是泣穷途。","韩氏有文曾饯汝，临行慎莫踌躇。","青灯双点照平湖。","蕉船从此逝，相共送陶朱。"]}],"cp-f5651b50":[{"t":"浣溪沙","f":"other","p":["残照西风一片愁。","疏杨画出六桥秋。","游人不上十三楼。","有泪金仙还泣汉，无心玉马已朝周。","平湖寂寂水空流。"]}]}