{"cp-26b610f5":[{"t":"相和歌辭 銅雀臺","f":"other","p":["北登銅雀上，西望青松郭。","繐帳空蒼蒼，陵田紛漠漠。","平生事已變，歌吹宛猶昨。","長袖拂玉麈，遺情結羅幕。","妾怨在朝露，君恩豈中薄。","高臺奏曲終，曲終淚橫落。"]},{"t":"相和歌辭 鳳臺曲","f":"other","p":["鳳臺何逶迤，嬴女管參差。","一旦綵雲至，身去無還期。","遺曲此臺上，世人多學吹。","一吹一落淚，至今憐玉姿。"]},{"t":"和宋之問下山歌","f":"other","p":["日云暮兮下嵩山，路連綿兮樹石間。","出谷口兮見明月，心裴回兮不能還。"]},{"t":"北使長城","f":"other","p":["秦世築長城，長城無極已。","暴兵四十萬，興工九千里。","死人如亂麻，白骨相撐委。","殫弊未云悟，窮毒豈知止。","胡塵未北滅，楚兵遽東起。","六國復囂囂，兩龍鬬觺觺。","卯金竟握讖，反璧俄淪祀。","仁義寢邦國，狙暴行終始。","一旦咸陽宮，翻爲漢朝市。"]},{"t":"鳳臺曲","f":"other","p":["鳳臺何逶迤，嬴女管參差。","一旦綵雲至，身去無還期。","遺曲此臺上，世人多學吹。","一吹一落淚，至今憐玉姿。"]},{"t":"銅雀臺","f":"other","p":["北登銅雀上，西望青松郭。","繐帳空蒼蒼，陵田紛漠漠。","平生事已變，歌吹宛猶昨。","長袖拂玉塵，遺情結羅幕。","妾怨在朝露，君恩豈中薄。","高臺奏曲終，曲終淚橫落。"]},{"t":"巫山","f":"other","p":["神女向高唐，巫山下夕陽。","裴回行作雨，婉孌逐荆王。","電影江前落，雷聲峽外長。","朝雲無處所，臺館曉蒼蒼。"]},{"t":"詠漢武帝（斯二七一七下同）","f":"other","p":["漢家中葉盛，六世有雄才。","廐馬三十萬，國容何壯裁（哉）！東歷瑯琊郡，北上單于臺。","好僊復寵戰，莫救茂陵●[一]。","（蔣云「●」以作隈爲是，「隈」有敗壞之義。","）（[一]「●」字不可識，疑當作「隈」。","劉云：「『隈』當是煨之誤。」","《說文》：煨，燼餘火也。","茂陵雖未聞焚燒之事，然陳沈烱《經通天臺奏漢武帝表》云：「茂陵玉椀，遂出人間，雲凌故基，與原田而每每；扶風餘趾，帶陵阜而芒芒」，亦正是茂陵煨燼的寫照了。","）。"]},{"t":"駕幸長安奉使先往檢察","f":"other","p":["奉使至京邑，戒塗歷險夷。","首旬發定鼎[一]，再信過灞池。","河山壯關輔，金火遞雄雌。","文物淪霸運，靈符啟聖青。","宸扆闊臨御，巡幸順謳思。","城闕生光彩，草樹含榮滋。","緹綺（騎）[二]紛沓襲，翠旗曳葳蕤。","童幼聞明主，耆老感盛儀。","輪袂交隱隱，廛陌滿熙熙。","微臣昧所識，觀俗書此詞。","（[一]劉云：「定鼎見《左傳》，成王定鼎於郟鄏，此處用以代表洛陽。","又考唐代洛陽城郭南而第二門名定鼎門，爲西行必由門戶。","」[二]依劉校。","）。"]},{"t":"滅胡","f":"other","p":["漢軍屢北喪，胡馬遂南駈。","羽書夜驚急，邊柝亂傳呼。","鬬軍卻不進，關城勢已孤。","黃雲塞沙落，（項云「落」當作「路」。","蔣云「落」爲「聚落」、「村落」之「落」。","）白刃斷交衢。","朔霧圍未解，鑿山泉尚枯。","伏波塞後援，都尉失前途。","亭障多墮毀，金鏃無金（全）[一]軀。","獨有山東客，上書圖滅胡。","（[一]俞云：「第二『金』是『全』之誤。","」）。"]},{"t":"君子有所思行","f":"other","p":["北上登渭原，南下望咸陽。","秦帝昔所據，按劍朝侯王。","踐山𪟖（劃）郊郭，濬流固墉隍。","左右羅將相，甲館臨康莊。","曲臺連閣道，錦幕接洞房。","荆國徵艷色，邯鄲選名倡。","一彈入雲漢，再歌斷君腸。","自矜青春日，王顏𢗞容光。","（「王顏」，蔣、項皆云當作「玉顏」。","「𢗞」，蔣云當作「恡」，惜也。","原卷作「恡」。","）安知綠苔滿，羅袖坐霑霜。","聲侈遽衰歇，盛愛且離傷。","豈唯毒身世，朝國亦淪亡。","（「朝國」，項疑當作「邦國」。","）物盈道先忌，（「物盈」，項云當作「惡盈」。","）履謙宇允臧。","獨有東陵子，種瓜青門旁。","（[一]俞云：「『𢗞』乃『恡』之簡體，即『悋，吝』。","」劉云：「當作『怯』。","」）。"]}],"cp-88d1af04":[{"t":"奉和聖製過溫湯","f":"other","p":["洛川方駐蹕，豐野暫停鑾。","湯泉恆獨涌，溫谷豈知寒。","漏鼓依巖畔，相風出樹端。","嶺煙遙聚草，山月迥臨鞍。","日用誠多幸，天文遂仰觀。"]}],"cp-19d185f2":[{"t":"贈別二首 一","f":"other","p":["江浦程千里，離尊淚數行。","無論吳與楚，俱是客他鄉。"]},{"t":"贈別二首 二","f":"other","p":["何處最悲辛，長亭臨古津。","往來舟檝路，前後別離人。"]},{"t":"句","f":"other","p":["他鄉生白髮，舊國有青山。"]}],"cp-179d3ab1":[{"t":"七老會詩","f":"other","p":["垂絲今日幸同筵，朱紫居身是大年。","賞景尚知心未退，吟詩猶覺力完全。","閑庭飲酒當三月，在席揮毫象七賢。","山茗煮時秋霧碧，玉杯斟處彩霞鮮。","臨堦花笑如歌妓，傍竹松聲當管弦。","雖未學窮生死訣，人間豈不是神仙。"]}],"cp-9fe44ab7":[{"t":"贈毛仙翁","f":"other","p":["存亡去住一壺中，兄事安期弟葛洪。","甲子已過千歲鶴，儀容方稱十年童。","心靈暗合行人數，藥力潛均造化功。","終待此身無繫累，武陵山下等黃公。"]}],"cp-7d244bd5":[{"t":"噴玉泉冥會詩八首 白衣叟途中吟二首 一","f":"other","p":["春草萋萋春水綠，野棠開盡飄香玉。","繡嶺宮前鶴髮人，猶唱開元太平曲。"]},{"t":"噴玉泉冥會詩八首 白衣叟途中吟二首 二","f":"other","p":["厭世逃名者，誰能荅姓名。","曾聞王樂否，眷取路傍情。"]},{"t":"噴玉泉冥會詩八首 白衣叟述甘棠館西楹詩","f":"other","p":["浮雲淒慘日微明，沈痛將軍負罪名。","白晝叫閽無近戚，縞衣飲氣只門生。","佳人暗泣填宮淚，廐馬連嘶換主聲。","六合茫茫皆漢土，此身無處哭田橫。"]},{"t":"噴玉泉冥會詩八首 白衣叟噴玉泉感舊遊書懷","f":"other","p":["樹色川光向晚晴，舊曾遊處事分明。","鼠穿月榭荆榛合，草掩花園畦壠平。","迹陷黃沙仍未寤，罪標青簡竟何名。","傷心谷口東流水，猶噴當時寒玉聲。"]},{"t":"噴玉泉冥會詩八首 四丈夫同賦 一","f":"other","p":["鳥啼鶯語思何窮，一世榮華一夢中。","李固有冤藏蠹簡，鄧攸無子續清風。","文章高韻傳流水，絲管遺音託草蟲。","春月不知人事改，閑垂光影照洿宮。"]},{"t":"噴玉泉冥會詩八首 四丈夫同賦 二","f":"other","p":["桃蹊李徑盡荒涼，訪舊尋新益自傷。","雖有衣衾藏李固，終無表疏雪王章。","羈魂尚覺霜風冷，朽骨徒驚月桂香。","天爵竟爲人爵悞，誰能高叫問蒼蒼。"]},{"t":"噴玉泉冥會詩八首 四丈夫同賦 三","f":"other","p":["落花寂寂草綿綿，雲影山光盡宛然。","壞室基摧新石鼠，瀦宮水引故山泉。","青雲自致慚天爵，白首同[歸]感昔賢。","惆悵林間中夜月，孤光曾照讀書筵。"]},{"t":"噴玉泉冥會詩八首 四丈夫同賦 四","f":"other","p":["新荆棘路舊衡門，又駐高車會一尊。","寒骨未沾新雨露，春風不長敗蘭蓀。","丹誠豈分埋幽壤，白日終希照覆盆。","珍重昔年金谷友，共來泉際話幽魂。"]}],"cp-c70eb653":[{"t":"浙東罷府西歸酬別張廣文皮先輩陸秀才","f":"other","p":["豈有頭風筆下痊，浪成蠻語向初筵。","蘭亭舊趾雖曾見，柯笛遺音更不傳。","照曜文星吳分野，留連花月晉名賢。","相逢只恨相知晚，一曲驪歌又幾年。"]},{"t":"和皮日休悼鸖 一","f":"other","p":["才子襟期本上清，陸雲家鸖伴閑情。","猶憐反顧五六里，何意忽歸十二城。","露滴誰聞高葉墜，月沈休藉半階明。","人聞華表堪留語，剩向秋風寄一聲。"]},{"t":"和皮日休悼鸖 二","f":"other","p":["道林曾放雪翎飛，應悔庭除閉羽衣。","料得王恭披鶴氅，倚吟猶待月中歸。"]},{"t":"醉中襲美先月中歸","f":"other","p":["休文雖即逃瓊液，阿鶩還須掩玉閨。","月落金雞一聲後，不知誰悔醉如泥。"]}],"cp-2c7e6664":[{"t":"題吉州龍溪","f":"other","p":["龍溪之山秀而峙，龍溪之水清無底。","狂風激烈翻春濤，薄霧冥濛溢清泚。","奔流百折銀河通，落花滾滾浮霞紅。","四時佳境不可窮，彷彿直與桃源通。"]}],"cp-465e23e6":[{"t":"蘭谿靈瑞觀","f":"other","p":["澄心坐清境，虛白生林端。","夜靜笑聲出，月明松影寒。","絳霞封藥竈，碧竇濺齋壇。","海樹幾回老，先生棊未殘。"]},{"t":"題赤松宮","f":"other","p":["松老赤松原，松間廟宛然。","人皆有兄弟，誰得共神仙。","雙鶴沖天去，羣羊化石眠。","至今丹井水，香滿北山邊。"]}],"cp-d0c22c36":[{"t":"贈錢起（題擬）","f":"other","p":["黃卷讀來今已老，白頭受屈不曾言。","（見《錢考功集》卷八《酬考功楊員外見贈佳句》自注引）（按：《郎官石柱題名》考功員外郎一欄殘泐過甚，存名僅五十二人，無楊姓者。","勞《考》卷十復自羣書採摭補遺，有楊於陵貞元八年後曾任此職，其時已較後。","頗此人即與錢起有過往之楊綰，然兩《唐書》本傳皆不云其任考外事。","姑存疑以俟考詳。","）。"]}],"cp-c553c532":[{"t":"撥櫂歌 一","f":"other","p":["千尺絲綸直下垂，一波纔動萬波隨。","夜靜水寒魚不食，滿船空載月明歸。","（按：《五燈會元》卷八載五代時建州白雲令弇禪師引後二句。","）。"]},{"t":"撥櫂歌 二","f":"other","p":["三十年來（《嘉禾志》作「二十餘年」）江（《五燈會元》作「海」）上遊，水清魚見不吞鉤。","釣竿斫盡重栽竹，不計工夫（《五燈會元》作「功程」，《嘉禾志》作「工程」）得便休。"]},{"t":"撥櫂歌 三","f":"other","p":["三（《嘉禾志》作「二」）十餘年（《五燈會元》作「年來」、《四溟詩話》作「年前」）坐釣臺，竿（《五燈會元》、《嘉禾志》、《四溟詩話》皆作「鉤」）頭往往得黃龍。","錦（《五燈會元》、《四溟詩話》作「金」）麟不遇空（《嘉禾志》作「虛」）勞力，收取（《四溟詩話》作「拾」）絲綸歸去來。","（以上三首，《嘉禾志》題作《自題三絕》）。"]},{"t":"撥櫂歌 四","f":"other","p":["一葉虛舟一副竿，了然無事坐煙灘。","忘得喪，任悲歡，却教人喚有多端。"]},{"t":"撥櫂歌 五","f":"other","p":["一任孤舟正又斜，乾坤何路指生涯。","拋歲月，臥煙霞，在處江山便是家。"]},{"t":"撥櫂歌 六","f":"other","p":["愚人未識主人公，終日孜孜恨不同。","到彼岸，出樊籠，元來祇是舊時翁。","（以上三首，《嘉禾志》題作《題松澤西亭三首》）。"]},{"t":"撥櫂歌 七","f":"other","p":["有一魚兮日溯洄（《五燈會元》作「偉莫裁」），混虛（《五燈會元》作「融」）包納信奇哉。","能變化，吐風雷，下線何曾釣得來。"]},{"t":"撥櫂歌 八","f":"other","p":["別人祇看採芙蓉，香氣長黏繞指風。","兩岸映，一船紅，何曾解染得虛空。"]},{"t":"撥櫂歌 九","f":"other","p":["問我生涯祇是船，子孫各自賭機緣。","不由地，不由天，除却簑衣無可傳。"]},{"t":"撥櫂歌 十","f":"other","p":["莫學他家弄釣船，海風起也不知邊。","風拍岸，浪掀天，不易安排得帖然。"]},{"t":"撥櫂歌 十一","f":"other","p":["大釣何曾離釣求，拋竿卷線却成愁。","活潑潑，樂悠悠，自是遲疑不下鉤。"]},{"t":"撥櫂歌 十二","f":"other","p":["靜在須禪動即禪，斷雲孤鶴兩蕭然。","煙浦畔，月川前，槁木形骸在一船。"]},{"t":"撥櫂歌 十三","f":"other","p":["莫道無修便不修，菩提癡坐若爲求？勤作櫂，慧爲舟，者箇男兒始出頭。"]},{"t":"撥櫂歌 十四","f":"other","p":["水色山光處處新，本來不俗不同塵。","著氣力，用精神，莫作虛生浪死人。"]},{"t":"撥櫂歌 十五","f":"other","p":["獨倚蘭橈入遠灘，江花漠漠水漫漫。","空鉤線，沒腥羶，那得凡魚都上竿。"]},{"t":"撥櫂歌 十六","f":"other","p":["揭却雲篷進却船，一竿雲影一潭煙。","既擲網，又拋筌，莫教倒被釣絲牽。"]},{"t":"撥櫂歌 十七","f":"other","p":["蒼苔滑淨坐忘機，截眼寒雲葉葉飛。","戴箬笠，掛簑衣，別無歸處是吾歸。","。"]},{"t":"撥櫂歌 十八","f":"other","p":["外却形骸放却情，蕭然孤坐一舟輕。","圓月上，四方明，不是奇人不易行。"]},{"t":"撥櫂歌 十九","f":"other","p":["世知吾懶懶原真，宇宙船中不管身。","烈香飲，落花茵，祖師元是箇閑人。"]},{"t":"撥櫂歌 二十","f":"other","p":["都大無心罔象間，此中那許是非關。","山兀兀，水潺潺，忙者自忙閑者閑。"]},{"t":"撥櫂歌 二十一","f":"other","p":["浪宕從來水郭間，高歌欹枕看遙山。","紅蓼岸，白蘋灣，肯被蘭橈使不閑。"]},{"t":"撥櫂歌 二十二","f":"other","p":["古釣先生鶴髮垂，穿波出浪不曾疑。","心蕩蕩，笑怡怡，長道無人畫得伊。"]},{"t":"撥櫂歌 二十三","f":"other","p":["動靜由來本兩空，誰教日夜強施功。","波渺渺，霧濛濛，却來江上隱雲中。"]},{"t":"撥櫂歌 二十四","f":"other","p":["媚俗無機獨任真，何須洗耳復澄神。","雲與月，友兼親，敢向浮漚任此身。"]},{"t":"撥櫂歌 二十五","f":"other","p":["逐塊追歡不識休，津梁渾不掛心頭。","霜葉落，岸花秋，却教漁父爲人愁。"]},{"t":"撥櫂歌 二十六","f":"other","p":["一片江雲倏忽開，翳空晴日絕塵埃。"]},{"t":"撥櫂歌 二十七","f":"other","p":["鼓櫂高歌自適情，音稀和寡不求名。","清風起，浪花平，也且隨流逐勢行。"]},{"t":"撥櫂歌 二十八","f":"other","p":["不妨綸線不妨鉤，祇要鉤輪得自由。","擲即擲，收即收，無蹤無跡樂悠悠。"]},{"t":"撥櫂歌 二十九","f":"other","p":["鉤下俄逢赤水珠，光明圓徹等清虛。","靜即出，覓還無，不在驪龍不在魚。"]},{"t":"撥櫂歌 三十","f":"other","p":["臥海拏雲勢莫知，優悠何處不相宜。","香象子，大龍兒，甚麽波濤颺得伊。"]},{"t":"撥櫂歌 三十一","f":"other","p":["雖慕求魚不食魚，網帘蓬戶本空無。","在世界，作凡夫，知聞祇是箇毘盧。"]},{"t":"撥櫂歌 三十二","f":"other","p":["香餌竿頭也不無，向來祇是釣名魚。","波沃日，浪涵虛，萬象牢籠號有餘。"]},{"t":"撥櫂歌 三十三","f":"other","p":["乾坤爲舸月爲篷，一帶雲山一逕風。","身放蕩，性靈空，何妨南北與西東。","。"]},{"t":"撥櫂歌 三十四","f":"other","p":["終日江頭理櫂間，忽然失濟若爲還。","灘急急，水潺潺，爭把浮生作等閑。"]},{"t":"撥櫂歌 三十五","f":"other","p":["有鶴翺翔出海風，往來蹤跡在虛空。","圖不得，弄何窮，日月還教沒此中。"]},{"t":"撥櫂歌 三十六","f":"other","p":["釣頭曾未曲些些，靜向江濱度歲華。","酌山茗，折蘆花，誰言埋沒在煙霞。"]},{"t":"撥櫂歌 三十七","f":"other","p":["吾自無心無事間，此心祇有水雲關。","攜釣竹，混塵寰，喧靜都來離又閑。"]},{"t":"撥櫂歌 三十八","f":"other","p":["晴川清瀨水橫流，瀟灑元同不繫舟。","長自在，任夷猶，將心隨逐幾時休。"]},{"t":"撥櫂歌 三十九","f":"other","p":["歐冶銛鋒價最高，海中收得用吹毛。","龍鳳繞，鬼神號，不見全牛可下刀。","（以上三十九首，均見嘉慶間刻本《機緣集》，原爲宋大觀四年風涇海會寺石刻。","轉錄自《詞學》第二期刊施蟄存先生《船子和尚撥櫂歌》。","宋明間收錄船子和尚詩偈的著作，筆者所見有：宋釋惠洪《冷齋夜話》卷五、胡仔《苕溪漁隱叢話前集》卷五六收第一首，宋釋慧明《五燈會元》卷五收其一、其二、其三、其七、其八、其九，共六首，宋吳聿《觀林詩話》收第三十九首，元至元《嘉禾志》卷三二收其一至其六，共六首，明謝榛《四溟詩話》卷三收第三首，楊慎《藝林伐山》卷十七收第一至第三首，今即據諸書所引出校。","）（〖1〗《機緣集》附石刻後呂益柔跋云：「雲間船子和尚嗣法藥山，飄然一舟，泛於華亭吳江洙涇之間。","夾山一見悟道。","嘗爲《撥櫂歌》，其傳播人口者纔一二首。","益柔於先子遺篇中得三十九首，屬詞寄意，脫然迥出塵網之外。","篇篇可觀，決非庸常學道輩所能亂真者。","因書以遺風涇海會卿者，俾鑱之石，以資禪客翫味云。","」〖2〗吳聿《觀林詩話》：「華亭船子和尚詩，少見於世，呂益柔刻三十九首於楓涇寺，云得其父遺編中。","……涪翁屢用其語。","」）。"]},{"t":"偈","f":"other","p":["本是釣魚船上客，偶力須髮著袈裟。","佛祖位中留不住，夜深依舊宿蘆花。","（見明楊慎《藝林伐山》卷十七《船子和尚四偈》）（〖1〗施蟄存先生云：「此首楊升庵所錄四偈之三，疑是僞作。","」）。"]}],"cp-0d154c0c":[{"t":"水调歌头","f":"other","p":["九月二十六，公相纪生辰。","橙黄橘绿时候，天气暖於春。","奎画有堂辉焕，中著台星一点，长伴寿星明。","衮衮有家庆，未羡古徐卿。","谢元枢，营绿野，避洪名。","六年裁剸国事，曾费几精神。","歇了傅岩霖雨，闲了孤舟野渡，旒冕合知心。","吾道苟尊尚，元不在蒲轮。"]}],"cp-ef1ce128":[{"t":"水调歌头","f":"other","p":["重过钓台路，风物故依然。","羊裘轩上，俯临清泚面孱颜。","仰见先生风节，更有两公名德，冰雪照人寒。","龙野方驰逐，鸿翼自孤骞。","酹壶觞，追往昔，笑华颠。","别来三纪，推排曾戴侍臣冠。","惭愧君恩难答，聊复守符重绾，敢叹客途艰。","少报期年政，行泛五湖船。"]}],"cp-85fd8596":[{"t":"沁园春","f":"other","p":["月晃西窗，风掀斗帐，晓来梦回。","见满川惊鹭，长空瑞鹤，联翩来下，翔舞徘徊。","旋放金磐承积块，更轻撼琼壶撩冻澌。","毡帏小，近宝炉兽炭，沈水兰煤。","寒威。","酒力相欺。","荐绿蚁霜螯左右持。","问岁岁祯祥，如何中断，年年梅月，因甚愆期。","上绀碧楼，城高百尺，看白玉虬龙奔四围。","纷争罢，正残鳞败甲，天上交飞。"]},{"t":"醉桃源・阮郎归","f":"other","p":["山翁可是爱登台。","看云日几回。","恨无语似谪仙才。","空教云去来。","思往事，引深杯。","长歌感壮怀。","霜风晚下扫阴霾。","天心宝鉴开。"]},{"t":"醉桃源・阮郎归","f":"other","p":["马蹄西路赏春妍。","重来十五年。","好山如带水如环。","红楼罨画闲。","人易老，景如前。","停杯俯逝川。","归舟回首望云烟。","秦人隔洞天。"]},{"t":"醉桃源・阮郎归","f":"other","p":["去年手种十株梅。","而今犹未开。","山翁一日走千迥。","今朝蝶也来。","高树杪，暗香微。","悭香越恼怀。","更烧银烛引春回。","英英露粉腮。"]},{"t":"蝶恋花","f":"other","p":["墙角栽梅分两下。","夹竹穿松，巧傍柴门亚。","不似西湖明月夜。","展开一片江南画。","老子寻芳心已罢。","为爱孤高，结约如莲社。","清静界中观物化。","憧憧门外驰车马。"]},{"t":"蝶恋花","f":"other","p":["天际行云红一缕。","无尽青山，江水悠悠去。","更上层楼凭远处。","凄凉今古悲三楚。","心事多端谁共语。","酒醒愁来，望望家何所。","薄宦漂零成久旅。","天涯却羡鸿遵渚。"]},{"t":"蝶恋花","f":"other","p":["姑射真仙蓬海会。","驭气乘龙，作意游方外。","冬后翦花飞素彩。","腊前陨璞抛团块。","幂幂锦云相映带。","川谷林峦，混一乾坤大。","白玉装成全世界。","江湖点染微瑕颣。"]},{"t":"蝶恋花","f":"other","p":["屈指瓜期犹渺渺。","羡子征鞍，去上长安道。","到得故园春正好。","桃腮杏脸迎门笑。","闻道难兄登显要。","雁子云宵，花萼应同调。","旧恨新愁须拼了。","功名趁取方年少。"]},{"t":"蝶恋花","f":"other","p":["眼约心期常未足。","邂逅今朝，暂得论心曲。","忽堕鲛珠红簌簌。","双眸翦水明如烛。","可恨匆匆归去速。","去去行云，望断凄心目。","何似当初情未熟。","免教添得愁千斛。"]},{"t":"蝶恋花","f":"other","p":["天色沈沈云色赭。","风扰阴寒，浩荡吹平野。","万斛珠玑天弃舍。","长空撒下鸣鸳瓦。","玉女凝愁金阕下。","褪粉残妆，和泪轻挥洒。","欲降尘凡飙驭驾。","翩翩白凤先来也。"]},{"t":"长相思","f":"other","p":["体夭夭。","步飘飘。","绶带金泥缕绛绡。","珑璁趁步摇。","浅霞消。","两峰遥。","斜插层楼金系腰。","花羞人面娇。"]},{"t":"长相思","f":"other","p":["展颦蛾。","抹流波。","并插玲珑碧玉梭。","松分两髻螺。","晓霜和。","冻轻呵。","拍罢阳春白雪歌。","偎人春意多。"]},{"t":"长相思","f":"other","p":["冒寒吹。","访琼姬。","行到青山遇玉肌。","凝情欲待谁。","山疏篱。","手同携。","踏月随香清夜归。","乘欢拨冻醅。"]},{"t":"浣溪沙","f":"other","p":["浅著铅华素净妆。","翩跹翠袖拂云裳。","傍人作意捧金觞。","曲度清悲云冉冉，花飞零乱月茫茫。","梦回人去似高唐。"]},{"t":"浣溪沙","f":"other","p":["直系腰围鹤间霞。","双垂项帕凤穿花。","新妆全学内人家。","惠性芳心谁得似，饶嗔□恶也还他。","只消凡事与饶些。"]},{"t":"清平乐","f":"other","p":["红尘久住。","仙驭凌波去。","本似行云无定处。","那更腊残风雨。","瑶芳片片轻飞。","但留青子栾枝。","孤负岁寒幽意，如今却与春宜。"]},{"t":"清平乐","f":"other","p":["灵心暗属。","髻垒黄金粟。","寂静虚堂情不足。","微步徘徊山麓。","蕊珠宫里新妆。","生香全似瑶芳。","应为莺花留恋，人间暂歇鸾凤。"]},{"t":"促拍满路花","f":"other","p":["名花无影迹，寒气日凄凉。","人间千万树，歇芬芳。","紫微宫女，仙驭降霓裳。","名在仙班簿，不属尘凡，洞天密锁云窗。","遗珰连宝珥，人间识天香。","凝寒承雨露，傲冰霜。","凌仙仙子，邂逅水云乡。","更约南枝友，游遍江南，共归三岛扶桑。"]},{"t":"谒金门","f":"other","p":["花满树。","两个黄鹂相语。","恰似碧城双玉女。","对歌还对舞。","可惜娟娟楚楚。","同伴彩云归去。","居士心如泥上絮。","那能无恨处。"]},{"t":"谒金门","f":"other","p":["嗟久客。","又见他乡寒食。","流水断桥春寂寂。","孤村烟火息。","白去红飞无迹。","千树总成新碧。","醉里伤春愁似织。","东风欺酒力。"]},{"t":"谒金门","f":"other","p":["芳思切，旧事不堪重说。","浓露凝香花喷血。","花心双蛱蝶。","燕语莺啼都歇。","又过清明时节。","记得离歌三两阕。","未歌先哽咽。"]},{"t":"谒金门","f":"other","p":["春又过。","那更雨摧风挫。","留得浅红三两朵。","竹梢烟雾锁。","把酒对花危坐。","多病多愁都可。","舞蝶游蜂迷道左。","惜春忙似我。"]},{"t":"谒金门","f":"other","p":["秋夜静。","屋上狂风初定。","两两啼蛄相答应。","灯蛾摇烛影。","枕上鸡声遥听。","起舞良宵偏永。","明日谩寻弓剑整。","衰颜重揽镜。"]},{"t":"谒金门","f":"other","p":["芳信拆。","漏泄东君消息。","帝殿宝炉烟未熄。","龙香飘片白。","点缀枯梢的皪。","疏影摇荡寒碧。","指与纤纤教自摘。","枝横云鬓侧。"]},{"t":"谒金门","f":"other","p":["天气暖。","开了荼䕷一半。","红日迟迟风拂面。","阶前花影乱。","俊雅风流不见。","定被莺花留恋。","千尺游丝舒又罥。","系人心上线。"]},{"t":"谒金门","f":"other","p":["歌罢奏。","敛步拂开罗袖。","宝扇轻摇香汗透。","软香沾素手。","小立偎人良久。","一寸娇波横溜。","心事未言眉已皱。","无端催劝酒。"]},{"t":"南乡子","f":"other","p":["斗笠棹边舟。","碧水湾头放自流。","尽日垂丝鱼不上，优游。","更觉心松奈得愁。","行客语沧洲。","笑道渔翁太拙休。","万事要求须有道，何由。","教与敲针换曲钩。"]},{"t":"南乡子","f":"other","p":["纵棹越溪船。","破浪冲涛到碧湾。","种就长堤千亩竹，无边。","插玉屯云满渭川。","平日乐归田。","不恋荣华不慕仙。","得个容身栖隐处，宽闲。","每日江边理钓竿。"]},{"t":"减字木兰花","f":"other","p":["烟云变化。","面面青山如展画。","俯对平川。","野水烟村远接天。","有时纵目。","景物繁华观不足。","月下风头。","一曲清讴博见楼。"]},{"t":"瑞鹤仙","f":"other","p":["南州春又到。","向腊尽冬残，冰姑先报。","芳心爱春早。","露生香馥馥，靓妆皎皎。","诗人最巧。","道竹外、斜枝更好。","旋移根引水，浇培松竹，凑成三妙。","回首。","当年客里，荆棘途中，幸陪欢笑。","闲愁似扫。","记风雪、关山道。","待飘花结子，和羹煮酒，还我山居送老。","那青红、浪蕊浮花，尽锄去了。"]},{"t":"瑞鹤仙","f":"other","p":["倚阑观四远。","近有客登临，故相磨难。","山形欠舒展。","小峰峦云树，晦明更变。","江淮楚甸。","又何曾、分明在眼。","但临深、自觉身高，未可便名博见。","休辨。","吾心乐处，不要他人，共同称善。","痴儿浅浅。","因他谩说一遍。","问还知宴坐，回光收视，大地河山尽现。","待於中、会得些时，举觞奉劝。"]},{"t":"瑞鹤仙","f":"other","p":["人生如意少。","谁得似仙翁，身名俱好。","亨衢腾踏早。","驾双旌五马，便居蓬岛。","闽山蜀道。","秉玉节、油幢屡到。","号当今、有脚阳春，处处变愁成笑。","尤妙。","晚陪论道。","密赞调元，虎符重剖。","去劳自保。","奉香火、归来了。","见煌煌甲第，两两龙驹，绿鬓朱颜未到。","是平生、种德阴功，自天有报。"]},{"t":"瑞鹤仙","f":"other","p":["金枝联玉叶。","世代有宗英，声华烨烨。","君侯更超绝。","抱不群才气，壮图英发。","津途轨辙。","□武上、青宵迥别。","自玉阶、契合君王，拍拍满怀风月。","奇绝。","身居萧散，志在功名，眼高天阔。","恩来魏阕。","长江上、驻旌节。","待胡尘有警，纶巾羽扇，谈笑周郎事业。","恁时看、国倚强宗，诏褒伟烈。"]},{"t":"瑞鹤仙","f":"other","p":["残梅飘簌簌。","看柳上春归，揉条新绿。","娇莺离幽谷。","弄弹簧清响，飞迁乔木。","年华迅速。","叹浮生、流晖转烛。","自春来、每每遨游，多办九霞醽醁。","溪北。","踏青微步，斗草慵眠，锦裀花褥。","铅华簇簇。","歌声妙、间丝竹。","爱一川好处，高山流水，不减城南杜曲。","笑平生、卓地无锥，老来富足。"]},{"t":"满江红","f":"other","p":["往事千端，都销道、衰翁宦拙。","今会得、人情物态，尽皆休说。","广厦尽堪舒笑傲，层楼又见凌空阔。","试闲思、画戟比衡门，谁优劣。","尘里事，无休歇。","楼上事、真奇绝。","有一川虚旷，万山环列。","识破古今如旦暮，肯将物我刚分别。","愿时时、与客坐楼心，谈风月。"]},{"t":"满江红","f":"other","p":["屈指重阳，有半月、犹零九日。","且停待、今宵月上，宝轮飞出。","有客最谙闲况味，无人会得真消息。","算何须、抵死要荣华，劳心力。","楼观迥、遥山碧。","槽窄小，真珠滴。","随分赏、闲亭别圃，好天良夕。","篱畔行看金蕊耀，林梢便见瑶芳白。","玩春来、夏去复秋冬，尘中客。"]},{"t":"满江红","f":"other","p":["小立危亭，风惨淡、斜阳满目。","望渺渺、湘江一派，楚山千簇。","芳草连云迷远树，断霞散绮飞孤骛。","感骚人、赋客向来词，愁如束。","磋远宦、甘微粟。","惊世事，伤浮俗。","且经营一醉，未怀荣辱。","君不见、渊明归去后，一觞自泛东篱菊。","仰高风、寂寞奠生刍，人如玉。"]},{"t":"满江红","f":"other","p":["忆惜西来，春已暮、馀寒犹力。","正迤逦、登山临水，未磋行役。","云笈偶寻高士传，桃川又访秦人迹。","向此时、游宦兴阑珊，归无策。","归计定，归心追。","惊换岁，犹为客。","还怅望、家山千里，迥无消息。","□□不堪泥路远，烟林赖有梅花白。","为孤芳、领略岁寒情，谁人识。"]},{"t":"满江红","f":"other","p":["物理分明，人事巧、元来是拙。","常自觉、满怀春意，向他谁说。","剩喜登临频眺望，那知出处成迂阔。","细闲思、萧散较贪痴，谁为劣。","高楼上、蝉声歇。","飞楝外，云行绝。","见明河星斗，半空森列。","领略光阴成赋咏，等闲酬唱休旌别。","要良辰、把酒倩佳宾，嘲风月。"]},{"t":"满江红","f":"other","p":["拍碎红牙，一声上、梁尘暗落。","纨扇掩、雏莺叶下，巧呈绰约。","字字只愁郎幸浅，声声似怨年华薄。","坐中人、相顾感幽怀，添萧索。","歌暂阕，杯交错。","人又去，情怀沪。","那堪听风雨，渭城吹角。","去去已离闽岭路，行行渐近滕王阁。","便无情、山海会相逢，坚心著。"]},{"t":"满江红","f":"other","p":["檀扳频催，双拈袖、飞来趁拍。","锦裀上、娇抬粉面，浅蛾脉脉。","鸾观莺窥秋水净，鸿惊凤翥祥云白。","看妖娆、体态与山精神，天仙谪。","鞓带紧，弓靴窄。","花压帽，云垂额。","□回雪、定拼醉倒，厌厌良夕。","明日恨随芳草远，回头目断遥山隔。","料多情、应也念行人，思佳客。"]},{"t":"满江红","f":"other","p":["墙下松筠，并手种、花窠尽著。","试屈指、一年前事，恍然如昨。","繁杏新荷春夏景，疏梅细菊秋冬约。","渭川翁、随分小生涯，些官爵。","分物我，争强弱。","都作梦，谁先觉。","好一条平路，是人迷却。","斑鬓已灰心里事，瘦滕谩卦瓢中药。","愿当今、四海九州人，同欢乐。"]},{"t":"满江红","f":"other","p":["雪压山颓，谁撒下、琼花玉蕊。","寒气凛、沈沈天籁，望迷千里。","群雀耐寒枯树顶，扁舟独钓平沙觜。","把江南、图画展开看，都难比。","台榭远、登临喜。","楼阁上，歌声起。","赏时光，居士独怜愁底。","安得四方寒畯彦，归吾广厦千间里。","但今生、此愿得从心，心休矣。"]},{"t":"满江红","f":"other","p":["惨惨枯梢，初疑似、真酥点滴。","见深红蒂萼，方认早梅消息。","粉艳牵连春意动，冰姿照映霜华白。","伴苍松、修竹似幽人，相寻觅。","香远近，枝南北。","幽涧畔，疏篱侧。","便佣儿贩妇，也知怜惜。","渭水渔翁方入社，西湖处士成陈迹。","爱平生、炯炯岁寒心，无今昔。"]},{"t":"江城子","f":"other","p":["年年腊后见冰姑。","玉肌肤。","点琼酥。","不老花荣，经岁转敷腴。","向背稀稠如画里，明月下、影疏疏。","江南有客问征途。","寄音书。","定来无。","且傍盆池，巧石倚浮图。","静对北山林处士，妆点就、小西湖。"]},{"t":"江城子","f":"other","p":["一钩新月下庭西。","绣帘低。","漏声迟。","小宴幽欢，依约似当时。","娇盼注人都不语，眉黛蹙，鬓云敧。","街槐阴下玉骢嘶。","苦相催。","醉中归。","可惜明朝，秋色满东篱。","只恐又成轻别也，情脉脉，恨凄凄。"]},{"t":"满庭芳","f":"other","p":["丹雘浮空，琉璃耀日，上云楼阁眈眈。","□□居士，燕坐息玄谈。","十载劳心问道，今悟罢、截日停参。","凝神处，九苞丹凤，翔舞在山南。","喃喃。","成障碍，千经万论，从此休贪。","且陶陶兀兀，对酒醺酣。","清兴有时狂放，扁舟上、绿水澄潭。","渔歌起，从他两岸，齐笑老翁憨。"]},{"t":"卜算子","f":"other","p":["人事几时穷，我性偏宜静。","世上谁无富贵心，到了须由命。","闲里且偷安，醉后休教醒。","醉里高歌妙入神，妙处君须听。"]},{"t":"卜算子","f":"other","p":["梅蕾破香时，雪后交光夜。","何处飞来两玉蛾，体态双闲雅。","纵目碧城楼，劝酒留云榭。","唱底仙家古道情，分付知音者。"]},{"t":"瑞鹧鸪","f":"other","p":["与君蹑足共凭阑。","俯视周回四面山。","目静鲁邦心渺渺，气吞梦泽意闲闲。","烟云变化更明晦，乌鹊忘机互往还。","唤取黄尘冠盖客，暂来徙倚片时间。"]},{"t":"瑞鹧鸪","f":"other","p":["几时芟棘翦蒿蓬。","付我天然地一弓。","乔木茂林森耸耸，遥岑叠嶂碧重重。","水心台榭超尘表，楼上乾坤跨域中。","黄鹤巴陵千古事，那知不是此衰翁。"]},{"t":"感皇恩","f":"other","p":["秋意满江湖，雨轻风熟。","上水扁舟片帆速。","远山低岸，贪看浅红深绿。","不知回柁尾，沧湾宿。","推枕起来，举杯相属。","休叹风尘为微禄。","几年行路，但觉登临不足。","且翻楚调入，清江曲。"]},{"t":"临江仙","f":"other","p":["忽忆裴公台上去，远空秋气棱棱。","万山一水秀还明。","此时三楚客，何意续骚经。","爱竹子犹参杖履，能诗候喜同登。","赓酬不尽古今情。","清风生白尘，侧月照疏星。"]},{"t":"好事近","f":"other","p":["风景好樵川，郭外三洲烟渚。","过尽古今清逸，奈天公不与。","地灵人意会符同，留待烟霞侣。","一棹轻舟开岸，弄滩声风雨。"]},{"t":"好事近","f":"other","p":["宿面浅匀妆，梅粉旋生春色。","绣草冠儿宫样，系丁香新缬。","凤檀槽上四条弦，轻□□□攧。","恰似寻阳江畔，话长安时节。"]},{"t":"鹊桥仙","f":"other","p":["银花千里，玉阶三尺，远近高低一色。","天公今岁被诗催，特地放、冬前四白。","梅梢竹外，频频轻撼，嫌乱瑶芳素质。","耐寒相对不胜清，毡帐底、偎红未得。"]},{"t":"木兰花慢","f":"other","p":["残红吹尽了，换新绿、染疏林。","正杜宇催归，行人贪路，天气轻阴。","江亭旧游宴处，但瑶山、数叠晚云深。","犹忆佳人敛黛，为予别泪盈襟。","而今。","旅况难禁。","逢胜概、懒登临。","念景熟难忘，情多易感，取次关心。","平明又西去也，望关山、古道马骎骎。","回首当年一梦，笑将浊酒重斟。"]},{"t":"木兰花慢","f":"other","p":["无言凭燕几，爱香袅、博山炉。","正暖日辉辉，晴云淡淡，千里平芜。","田家尽收刈了，见牛羊、下垅暝烟孤。","闻说丰年景致，老农击壤呜呜。","狂夫。","素乏良图。","从上策、赋归欤。","有千亩松筠，三洲风月，尽随吾初。","凭谁去西塞岸，问玄真、此意果如何。","寂寞无人共乐，醉乡是我华胥。"]},{"t":"木兰花慢","f":"other","p":["对轩辕古镜，照华发、短刁骚。","念壮岁心情，平生志气，可笑徒劳。","云中谩夸魏尚，请休论、定远说班超。","总是黄粱一梦，怎如尘外逍遥。","蛮徭。","洞入云宵。","算无分、到仙曹。","愿归隐闽山，来临渭水，葺个云巢。","楼居共、真仙伴侣，又有时、混迹入渔樵。","且恁随缘玩世，帝乡路觉迢迢。"]},{"t":"木兰花慢","f":"other","p":["朝天门外路，路坦坦、走瑶京。","悔年少狂图，争名远宦，为米孤征。","星星。","半凋鬓发，事千端、回首只堪惊。","居士新来悟也，渭川小隐初成。","临清。","巧创幽亭。","真富贵、享安荣。","有猿鸟清讴，松篁森卫，桧柏双旌。","蛙鸣。","自然鼓吹，粲林华、前后锦围屏。","须信早朝鸡唱，未如夜枕滩声。"]},{"t":"木兰花慢","f":"other","p":["平生花恨少，又那得、酒中愁。","自禅板停参，蒲团悟罢，身世忘忧。","南柯旧时太守，尽当年、富贵即时休。","莫羡痴儿小子，心心念念封侯。","优游。","取次凝眸。","春浩浩、思悠悠。","爱万木欣荣，幽泉流注，好鸟勾舟，感生生、自然造化，玩吾心、此外复何求。","应有知音共赏，定当一语相投。"]},{"t":"柳梢青","f":"other","p":["叶下云行，亭皋风静，凉雨丝丝。","断雁孤鸣，寒蛩相应，寂寂书帏。","蒲团纸帐兰台。","梦不到、邯郸便回。","蚁穴荣华，人间功业，都恼人怀。"]},{"t":"鹧鸪天","f":"other","p":["竹树萧萧屋数椽。","平湖漫漫纳通川。","有时竹杖芒鞋至，醉著山光水色间。","成小隐，未经年。","功名夷路稳加鞭。","逢时且数中书考，他日还寻独乐园。"]},{"t":"鹧鸪天","f":"other","p":["记得追游故老家。","红莲幕府在长沙。","放船桥口秋随月，走马春园夜踏花。","思往昔，谩咨磋。","几番魂梦转天涯。","葵轩老子今何在，岳麓风雩噪暮鸦。"]},{"t":"鹧鸪天","f":"other","p":["一夜春寒透锦帏。","满庭花露起多时。","垒金梳子双双耍，铺翠花儿袅袅垂。","人去后，信来稀。","等闲屈指数归期。","门前恰限行人至，喜鹊如何圣得知。"]},{"t":"鹧鸪天","f":"other","p":["日日楼心与画眉。","松分蝉翅黛云低。","象牙白齿双梳子，驼骨红纹小棹篦。","朝暮宴，浅深杯。","更阑生怕下楼梯。","徐娘怪我今疏懒，不及庐郎年少时。"]},{"t":"鹧鸪天","f":"other","p":["纸帐虚明好醉眠。","博山轻袅水沉烟。","了知世上都如梦，须信壶中别有天。","知我者，为君言。","道人有个好因缘。","丹成有日归云路，且最梅花作地仙。"]},{"t":"点绛唇","f":"other","p":["满路梅花，为谁开遍春风萼。","短亭萧索。","草草传杯酌。","送子先归，我羡辽东鹤。","他年约。","瘦藤芒履。","共子同丘壑。"]},{"t":"点绛唇","f":"other","p":["日月无根，循环常共天难老。","世间扰扰。","只见闲烦恼。","满酌高吟，便是今生了。","还知道。","旧时官好。","几个新华表。"]},{"t":"点绛唇","f":"other","p":["一叶扁舟，浮家来向江边住。","这回归去。","作个渔樵侣。","不挂征帆，也莫遥双橹。","天涯路。","云山烟渚。","总是留人处。"]},{"t":"点绛唇","f":"other","p":["桂子飘香，江南秋老霜风作。","自怜漂泊。","几度伤离索。","孤馆迢迢，满引村醪酌。","情无著。","好音难托。","又失黄花约。"]},{"t":"点绛唇","f":"other","p":["瑞气盈门，神仙谪下看看到。","已知消耗。","弧矢呈祥了。","种德阴功，自有多男报。","还知道。","果生蓬岛。","不比人间早。"]},{"t":"鱼游春水","f":"other","p":["林梢听布谷。","郭外舒怀仍快目。","平田浩荡，虢虢泉鸣暗谷。","香稻吐芒针棘细，秀麦遥风波浪绿。","山童野老，意亲情热。","我待休官弃禄。","屏迹幽闲安退缩。","渭三千亩修篁，巑巑绀玉。","顾盼滩流萦八节，呼吸湖光穿九曲。","贪求自乐，尽忘尘俗。"]},{"t":"霜天晓角","f":"other","p":["晓来风作。","病怯春衫薄。","郭外溪山明秀，红尘里、自拘缚。","村酒频斟酌。","野花遍绰约。","十载人非物是，惊回首、梦初觉。"]},{"t":"虞美人","f":"other","p":["疏风摆撼芙蓉沼。","垅上梅英小。","谁家姊妹去寻芳。","粉面云鬟参杂、汉宫妆。","邯郸奏罢宫中乐。","邂逅同杯酌。","老来花酒制颓龄。","为爱嫣然娇靥、斗盈盈。"]},{"t":"虞美人","f":"other","p":["年年冬后心情快。","常是留宾醉。","尊前笑靥粲金钿。","更有半黄枨橘、满堆磐。","人人爱道休官去。","总是闲言语。","古今文士与贤才。","为甚独高陶令、赋归来。"]},{"t":"虞美人","f":"other","p":["横波清翦西湖水。","黛拂吴山翠。","藕丝衫子水沈香。","坐久冰肌玉骨、起微凉。","金徽泛柳听佳句。","叠叠胎仙舞。","曲终松下小磐桓。","风露泠泠、直欲便骖鸾。"]},{"t":"菩萨蛮","f":"other","p":["遥山几叠天边碧。","故教遮断天涯客。","楼倚暮云端。","春风罗袖寒。","与君千里别。","共此关山月。","皓月一般明。","君心怎敢凭。"]},{"t":"菩萨蛮","f":"other","p":["岭猿啸罢千山碧。","小庵虚室团团白。","庵在小山头。","从来少客游。","道人方打坐。","举袖来迎我。","问我此来因。","拈花与道人。"]},{"t":"南歌子","f":"other","p":["湛露凉亭馆，香风散芰荷。","晚来月色似金波。","间绿围红、同伴雪儿歌。","年少风流足，情深欢会多。","佳人月下拜嫦娥。","不似隔年牛女、望星河。"]},{"t":"八声甘州","f":"other","p":["自秋来、多病意无聊，不作渭山游。","想兰菊凋疏，松筠茂密，亭馆清幽。","四望遥山万叠，叠叠翠光浮。","人道蓬莱岛，仿佛瀛洲。","居士心迷丘壑，念迂疏老懒，难觅封侯。","看才能成事业，且自抽头。","携老稚、团栾百口，要他年、在此作菟裘。","无言也，此生心事，都付东流。"]},{"t":"如梦令","f":"other","p":["花上娇莺哑咤。","著色江南图画。","可惜好春风，有酒无人同把。","拚舍。","拚舍。","独醉好天良夜。"]},{"t":"如梦令","f":"other","p":["王谢堂前旧燕。","毕竟情高意远。","只恐宠恩深，后会不教人见。","深劝。","深劝。","不枉追欢一遍。"]},{"t":"如梦令","f":"other","p":["梅雪渐当时候。","访问全无消耗。","凭杖小阳春，催取南枝先到。","然后。","然后。","雪月交光同照。"]},{"t":"西江月","f":"other","p":["日日齐眉举案，年年劝酒持觥。","今年著意寿卿卿。","幼稚绵绵可庆。","官冷未尝贫贱，家肥胜似功名。","所为方便合人情。","管取前途更永。"]},{"t":"渔家傲","f":"other","p":["长记浔阳江上宴。","庚公楼上凭阑遍。","北望淮山连楚甸。","真伟观。","中原气象依稀见。","漂泊江湖波浪远。","依然身在蛮溪畔。","愁里不知时节换。","春早晚。","杜娟声里飞花满。"]},{"t":"渔家傲","f":"other","p":["闻道西洲梅已放。","几时乘兴同寻访。","稚子携壶翁策杖。","徐徐往。","青山绿水皆堪赏。","满月当空川晃晃。","却呼艇子遥双桨。","几阵浓香新酝酿。","波溶漾。","宛然身在西湖上。"]},{"t":"渔家傲","f":"other","p":["特为梅花来渭水。","有人折得横梢至。","粉毖香悭春意未。","多应是。","江南信息争先寄。","水绿山青风日美。","此时正惬幽人意。","驱使风光佳句里。","□满纸。","却将旧日诗词比。"]},{"t":"杏花天","f":"other","p":["当年悔我抛生计。","趁升斗、蛮乡远地。","谁知事向无心起。","回首邯郸梦里。","风雪满□□□□。","最好处、吴头楚尾。","青山本是强人意。","更时见、梅花助美。"]}],"cp-092bb222":[{"t":"小重山令・小重山","f":"other","p":["人绕湘皋月坠时。","斜横花树小，浸愁漪。","一春幽事有谁知。","东风冷、香远茜裙归。","鸥去昔游非。","遥怜花可可，梦依依。","九疑云杳断魂啼。","相思血，都沁绿筠枝。"]},{"t":"江梅引・江城梅花引","f":"other","p":["人间离别易多时。","见梅枝。","忽相思。","几度小窗，幽梦手同携。","今夜梦中无觅处，漫徘徊。","寒侵被、尚未知。","湿红恨墨浅封题。","宝筝空、无雁飞。","俊游巷陌，算空有、古木斜晖。","旧约扁舟，心事已成非。","歌罢淮南春草赋，又萋萋。","漂零客、泪满衣。"]},{"t":"蓦山溪","f":"other","p":["与鸥为客。","绿野留吟屐。","雨行柳垂阴，是当日、仙翁手植。","一亭寂寞。","烟外带愁横，荷苒苒，展凉云，横卧虹千尺。","才因老尽，秀句君休觅。","万绿正迷人，更愁入、山阳夜笛。","百年心事，惟有玉阑知，吟未了，放船回，月下空相忆。"]},{"t":"莺声绕红楼","f":"other","p":["十亩梅花作雪飞。","冷香下、携手多时。","两年不到断桥西。","长笛为予吹。","人妒垂杨绿，春风为、染作仙衣。","垂杨却又妒腰枝。","近前舞丝丝。"]},{"t":"鬲溪梅令","f":"other","p":["好花不与殢香人。","浪粼粼。","又恐春风归去绿成阴。","玉钿何处寻。","木兰双桨梦中云。","小横陈。","漫向孤山山下觅盈盈。","翠禽啼一春。"]},{"t":"阮郎归","f":"other","p":["红云低压碧玻璃。","惺惚花上啼。","静看楼角拂长枝。","朝寒吹翠眉。","休涉笔，且裁诗。","年年风絮时。","绣衣夜半草符移。","月中双桨归。"]},{"t":"阮郎归","f":"other","p":["旌阳宫殿昔徘徊。","一坛云叶垂。","与君闲看壁间题。","夜凉笙鹤期。","茅店酒，寿君时。","老枫临路歧。","年年强健得追随。","名山游遍归。"]},{"t":"好事近","f":"other","p":["凉夜摘花钿，苒苒动摇云绿。","金络一团香露，正纱厨人独。","朝来碧缕放长穿，钗头挂层玉。","记得如今时候，正荔枝初熟。"]},{"t":"点绛唇","f":"other","p":["燕雁无心，太湖西畔随云去。","数峰清苦。","商略黄昏雨。","第四桥边，拟共天随住。","今何许。","凭栏怀古。","残柳参差舞。"]},{"t":"点绛唇","f":"other","p":["金谷人归，绿扬低扫吹笙道。","数声啼鸟。","也学相思调。","月落潮生，掇送刘郎老。","淮南好。","甚时重到。","陌上生春草。"]},{"t":"虞美人","f":"other","p":["西园曾为梅花醉。","叶翦春云细。","玉笙凉夜隔帘吹。","卧看花梢摇动、一枝枝。","娉娉袅袅教谁惜。","空压纱巾侧。","沈香亭北又青苔。","唯有当时蝴蝶、自飞来。"]},{"t":"虞美人","f":"other","p":["摩挲紫盖峰头石。","上瞰苍崖立。","玉盘摇动半崖花。","花树扶蔬、一半白云遮。","盈盈相望无由摘。","惆怅归来屐。","而今仙迹杳难寻。","那日青楼、曾见似花人。"]},{"t":"忆王孙","f":"other","p":["冷红叶叶下塘秋。","长与行云共一舟。","零落江南不自由。","两绸缪。","料得吟鸾夜夜愁。"]},{"t":"少年游","f":"other","p":["双螺未合，双蛾先敛，家在碧云西。","别母情怀，随郎滋味，桃叶渡江时。","扁舟载了，匆匆归去，今夜泊前溪。","杨柳津头，梨花墙外，心事两人知。"]},{"t":"鹧鸪天","f":"other","p":["京洛风流绝代人。","因何风絮落溪津。","笼鞋浅出鸦头袜，知是凌波漂渺身。","红乍笑，绿长嚬。","与谁同度可怜春。","鸳鸯独宿何曾惯，化作西楼一缕云。"]},{"t":"鹧鸪天","f":"other","p":["曾共君侯历聘来。","去年今日踏莓苔。","旌扬宅里疏疏磬。","挂屩枫前草草杯。","呼煮酒，摘青梅。","今年官事莫徘徊。","移家径入蓝田县，急急船头打鼓催。"]},{"t":"鹧鸪天","f":"other","p":["柏绿椒红事事新。","隔篱灯影贺年人。","三茅钟动西窗晓，诗鬓无端又一春。","慵对客，缓开门。","梅花闲伴老来身。","娇儿学作人间字，郁垒神荼写未真。"]},{"t":"鹧鸪天","f":"other","p":["巷陌风光纵赏时。","笼纱未出马先嘶。","白头居士无呵殿，只有乘肩小女随。","花满市，月侵衣。","少年情事老来悲。","沙河塘上春寒浅，看了游人缓缓归。"]},{"t":"鹧鸪天","f":"other","p":["忆昨天街预赏时。","柳悭梅小未教知。","而今正是欢游夕，却怕春寒自掩扉。","帘寂寂，月低低。","旧情惟有绛都词。","芙蓉影暗三更后，卧听邻娃笑语归。"]},{"t":"鹧鸪天","f":"other","p":["肥水东流无尽期。","当初不合种相思。","梦中未比丹青见，暗里忽惊山鸟啼。","春未绿，鬓先丝。","人间别久不成悲。","谁教岁岁红莲夜，两处沈吟各自知。"]},{"t":"鹧鸪天","f":"other","p":["辇路珠帘两行垂。","千枝银烛舞僛僛。","东风历历红楼下，谁识三生杜牧之。","欢正好，夜何其。","明朝春过小桃枝。","鼓声渐远游人散，惆怅归来有月知。"]},{"t":"夜行船","f":"other","p":["略彴横溪人不度。","听流澌、佩环无数。","屋角垂枝，船头生影，算唯有、春知处。","回首江南天欲暮。","折寒香、倩谁传语。","玉笛无声，诗人有句，花休道、轻分付。"]},{"t":"杏花天","f":"other","p":["绿丝低拂鸳鸯浦。","想桃叶、当时唤渡。","又将愁眼与春风，待去。","倚兰桡、更少驻。","金陵路。","莺吟燕舞。","算潮水、知人最苦。","满汀芳草不成归，日暮。","更移舟、向甚处。"]},{"t":"醉吟商小品・小品","f":"other","p":["又正是春归，细柳暗黄千缕。","暮鸦啼处。","梦逐金鞍去。","一点芳心休诉。","琵琶解语。"]},{"t":"玉梅令","f":"other","p":["疏疏雪片。","散入溪南苑。","春寒锁、旧家亭馆。","有玉梅几树，背立怨东风，高花未吐，暗香已远。","公来领略，梅花能劝。","花长好、愿公更健。","便揉春为酒，翦雪作新诗，拚一日、绕花千转。"]},{"t":"踏莎行","f":"other","p":["燕燕轻盈，莺莺娇软。","分明又向华胥见。","夜长争得薄情知，春初早被相思染。","别后书辞，别时针线。","离魂暗逐郎行远。","淮南皓月冷千山，冥冥归去无人管。"]},{"t":"诉衷情","f":"other","p":["石榴一树浸溪红。","零落小桥东。","五日凄凉心事，山雨打船篷。","谙世味，楚人弓。","莫忡忡。","白头行客，不采苹花，孤负薰风。"]},{"t":"浣溪沙","f":"other","p":["著酒行行满袂风。","草枯霜鹘落晴空。","销魂都在夕阳中。","恨入四弦人欲老，梦寻千驿意难通。","当时何似莫匆匆。"]},{"t":"浣溪沙","f":"other","p":["春点疏梅雨后枝。","翦灯心事峭寒时。","市桥携手步迟迟。","蜜炬来时人更好，玉笙吹彻夜何其。","东风落靥不成归。"]},{"t":"浣溪沙","f":"other","p":["钗燕笼云晚不忺。","拟将裙带系郎船。","别离滋味又今年。","杨柳夜寒犹自舞，鸳鸯风急不成眠。","些儿闲事莫萦牵。"]},{"t":"浣溪沙","f":"other","p":["雁怯重云不肯啼。","画船愁过石塘西。","打头风浪恶禁持。","春浦渐生迎棹绿，小梅应长亚门枝。","一年灯火要人归。"]},{"t":"浣溪沙","f":"other","p":["花里春风未觉时。","美人呵蕊缀横枝。","隔帘飞过蜜蜂儿。","书寄岭头封不到，影浮杯面误人吹。","寂寥惟有夜寒知。"]},{"t":"浣溪沙","f":"other","p":["翦翦寒花小更垂。","阿琼愁里弄妆迟。","东风烧烛夜深归。","落蕊半黏钗上燕，露黄斜映鬓边犀。","老夫无味已多时。"]},{"t":"霓裳中序第一","f":"other","p":["亭皋正望极。","乱落江莲归未得。","多病却无气力。","况纨扇渐疏，罗衣初萦。","流光过隙。","叹杏梁、双燕如客。","人何在，一帘淡月，仿佛照颜色。","幽寂。","乱蛩吟壁。","动庾信、清愁似织。","沈思年少浪迹。","笛里关山，柳下坊陌。","坠红无信息。","漫暗水，涓涓溜碧。","漂零久，而今何意，醉卧酒垆侧。"]},{"t":"庆宫春・高阳台","f":"other","p":["双桨莼波，一蓑松雨，暮愁渐满空阔。","呼我盟鸥，翩翩欲下，背人还过木末。","那回归去，荡云雪、孤舟夜发。","伤心重见，依约眉山，黛痕低压。","采香径里春寒，老子婆娑，自歌谁答。","垂虹西望，飘然引去，此兴平生难遏。","酒醒波远，政凝想、明珰素袜。","如今安在，唯有阑干，伴人一霎。"]},{"t":"齐天乐","f":"other","p":["庾郎先自吟愁赋。","凄凄更闻私语。","露湿铜铺，苔侵石井，都是曾听伊处。","哀音似诉。","正思妇无眠，起寻机杼。","曲曲屏山，夜凉独自甚情绪。","西窗又吹暗雨。","为谁频断续，相和砧杵。","候馆迎秋，离宫吊月，别有伤心无数。","豳诗漫与。","笑篱落呼灯，世间儿女。","写入琴丝，一声声更苦。"]},{"t":"满江红","f":"other","p":["仙姥来时，正一望、千倾翠澜。","旌旗共、乱云俱下，一依前山。","命驾群龙金作轭，相从诸娣玉为冠。","向夜深、风定悄无人，闻佩环。","神奇处，君试看。","奠淮右，诅江南。","遣六丁雷电，别守东关。","却笑英雄无好手，一篙春水走曹瞒。","又怎知、人在小红楼，帘影间。"]},{"t":"一萼红","f":"other","p":["古城阴。","有官梅几许，红萼未宜簪。","池面冰胶，墙腰雪老，云意还又沈沈。","翠藤共、闲穿径竹，渐笑语、惊起卧沙禽。","野老林泉，故王台榭，呼唤登临。","南去北来何事，荡湘云楚水，目极伤心。","朱户黏鸡，金盘簇燕，空叹时序侵寻。","记曾共，西楼雅集，想垂杨、还袅万丝金。","待得归鞍到时，只怕春深。"]},{"t":"念奴娇","f":"other","p":["闹红一舸，记来时、尝与鸳鸯为侣。","三十六陂人未到，水佩风裳无数。","翠叶吹凉，玉容销酒，更洒菰蒲雨。","嫣然摇动，冷香飞上诗句。","日暮。","青盖亭亭，情人不见，争忍凌波去。","只恐舞衣寒易落，愁入西风南浦。","高柳垂阴，老鱼吹浪，留我花间住。","田田多少，几回沙际归路。"]},{"t":"念奴娇","f":"other","p":["楚山修竹，自娟娟、不受人间袢暑。","我醉欲眠伊伴我，一枕凉生如许。","象齿为材，花藤为面，终是无真趣。","梅风吹溽，此君直恁清苦。","须信下榻殷勤，け然成梦，梦与秋相遇。","翠袖佳人来共看，漠漠风烟千亩。","蕉叶窗纱，荷花池馆，别有留人处。","此时归去，为君听尽秋雨。"]},{"t":"眉妩","f":"other","p":["看垂杨连苑，杜若侵沙，愁损未归眼。","信马青楼去，重帘下，娉婷人妙飞燕。","翠尊共款。","听艳歌、郎意先感。","便携手、月地云阶里，爱良夜微暖。","无限。","风流疏散。","有暗藏弓履，偷寄香翰。","明日闻津鼓，湘江上，催人还解春缆。","乱红万点。","怅断魂、烟水遥远。","又争似相携，乘一舸、镇长见。"]},{"t":"月下笛","f":"other","p":["与客携壶，梅花过了，夜来风雨。","幽禽自语。","啄香心、度墙去。","春衣都是柔荑翦，尚沾惹、残茸半缕。","怅玉钿似扫，朱门深闭，再见无路。","凝伫。","曾游处。","但系马垂杨，认郎鹦鹉。","扬州梦觉，彩云飞过何许。","多情须倩梁间燕，问吟袖、弓腰在否。","怎知道，误了人，年少自恁虚度。"]},{"t":"清波引","f":"other","p":["冷云迷浦。","倩谁唤、玉妃起舞。","岁华如许。","野梅弄眉妩。","屐齿印苍藓，渐为寻花来去。","自随秋雁南来，望江国、渺何处。","新诗漫与。","好风景、长是暗度。","故人知否。","抱幽恨难语。","何时共渔艇，莫负沧浪烟雨。","况有清夜啼猿，怨人良苦。"]},{"t":"法曲献仙音","f":"other","p":["虚阁笼寒，小帘通月，暮色偏怜高处。","树隔离宫，水平驰道，湖山尽入尊俎。","奈楚客淹留久，砧声带愁去。","屡回顾。","过秋风、未成归计。","谁念我、重见冷枫红舞。","唤起淡妆人，问逋仙、今在何许。","象笔鸾笺，甚而今、不道秀句。","怕平生幽恨，化作沙边烟雨。"]},{"t":"琵琶仙・自度曲","f":"other","p":["双桨来时，有人似、旧曲桃根桃叶。","歌扇轻约飞花，蛾眉正奇绝。","春渐远、汀洲自绿，更添了、几声啼鴂。","十里扬州，三生杜牧，前事休说。","又还是、宫烛分烟，奈愁里、匆匆换时节。","都把一襟芳思，与空阶榆荚。","千万缕、藏鸦细柳，为玉尊、起舞回雪。","想见西出阳关，故人初别。"]},{"t":"玲珑四犯","f":"other","p":["叠鼓夜寒，垂灯春浅，匆匆时事如许。","倦游欢意少，俯仰悲今古。","江淹又吟恨赋。","记当时、送君南浦。","万里乾坤，百年身世，唯有此情苦。","扬州柳，垂官路。","有轻盈换马，端正窥户。","酒醒明月下，梦逐潮声去。","文章信美知何用，漫赢得、天涯羁旅。","教说与。","春来要、寻花伴侣。"]},{"t":"侧犯","f":"other","p":["恨春易去。","甚春却向扬州住。","微雨。","正茧栗梢头弄诗句。","红桥二十四，总是行云处。","无语。","渐半脱宫衣笑相顾。","金壶细叶，千朵围歌舞。","谁念我、鬓成丝，来此共尊俎。","后日西园，绿阴无数。","寂寞刘郎，自修花谱。"]},{"t":"水龙吟","f":"other","p":["夜深客子移舟处，两两沙禽惊起。","红衣入浆，青灯摇浪，微凉意思。","把酒临风，不思归去，有如此水。","况茂林游倦，长干望久，芳心事、箫声里。","屈指归期尚未。","鹊南飞、有人应喜。","画栏桂子，留香小待，提携影底。","我已情多，十年幽梦，略曾如此。","甚谢郎、也恨飘零，解道月明千里。"]},{"t":"探春慢","f":"other","p":["衰草愁烟，乱鸦送日，风沙回旋平野。","拂雪金鞭，欺寒茸帽，还记章台走马。","谁念飘零久，漫赢得、幽怀难写。","故人清沔相逢，小窗闲共情话。","长恨离多会少，重访问竹西，珠泪盈把。","雁碛波平，渔汀人散，老去不堪游冶。","无奈苕溪月，又照我、扁舟东下。","甚日归来，梅花零乱春夜。"]},{"t":"八归","f":"other","p":["芳莲坠粉，蔬桐吹绿，庭院暗雨乍歇。","无端抱影销魂处，还见筱墙萤暗，藓阶蛩切。","送客重寻西去路，问水面、琵琶谁拨。","最可惜、一片江山，总付与啼鴂。","长恨相从未款，而今何事，又对西风离别。","渚寒烟淡，棹移人远，缥缈行舟如叶。","想文君望久，倚竹愁生步罗袜。","归来后、翠尊双饮，下了珠帘，玲珑闲看月。"]},{"t":"解连环","f":"other","p":["玉鞭重倚。","却沈吟未上，又萦离思。","为大乔、能拨春风，小乔妙移筝，雁啼秋水。","柳怯云松，更何必、十分梳洗。","道郎携羽扇，那日隔帘，半面曾记。","西窗夜凉雨霁。","叹幽欢未足，何事轻弃。","问后约、空指蔷薇，算如此溪山，甚时重至。","水驿灯昏，又见在、曲屏近底。","念唯有、夜来皓月，照伊自睡。"]},{"t":"喜迁莺慢・喜迁莺","f":"other","p":["玉珂朱组。","又占了、道人林下真趣。","窗户新成，青红犹润，双燕为君胥宇。","秦淮贵人宅第，问谁记、六朝歌舞。","总付与、在柳桥花馆，玲珑深处。","居士。","闲记取。","高卧未成，且种松千树。","觅句堂深，写经窗静，他日任听风雨。","列仙更教谁做，一院双成俦侣。","世间住。","且休将鸡犬，云中飞去。"]},{"t":"摸鱼儿","f":"other","p":["向秋来、渐疏班扇，雨声时过金井。","堂虚已放新凉入，湘竹最宜敧枕。","闲记省。","又还是、斜河旧约今再整。","天风夜冷。","自织锦人归，乘槎客去，此意有谁领。","空赢得，今古三星炯炯。","银波相望千顷。","柳州老矣犹儿戏，瓜果为伊三请。","云路回。","漫说道、年年野鹊曾并影。","无人与问。","但浊酒相呼，疏帘自卷，微月照清饮。"]},{"t":"扬州慢","f":"other","p":["淮左名都，竹西佳处，解鞍少驻初程。","过春风十里，尽荠麦青青。","自胡马窥江去后，废池乔木，犹厌言兵。","渐黄昏，清角吹寒，都在空城。","杜郎俊赏，算而今，重到须惊。","纵豆蔻词工，青楼梦好，难赋深情。","二十四桥仍在，波心荡、冷月无声。","念桥边红药，年年知为谁生。"]},{"t":"长亭怨慢","f":"other","p":["渐吹尽、枝头香絮。","是处人家，绿深门户。","远浦萦回，暮帆零乱向何许。","阅人多矣，谁得似、长亭树。","树若有情时，不会得、青青如此。","日暮。","望高城不见，只见乱山无数。","韦郎去也，怎忘得、玉环分付。","第一是、早早归来，怕红萼、无人为主。","算空有并刀，难翦离愁千缕。"]},{"t":"淡黄柳","f":"other","p":["空城晓月。","吹入垂杨陌。","马上单衣寒恻恻。","看尽鹅黄嫩绿，都是江南旧相识。","正岑寂。","明朝又寒食。","强携酒、小桥宅，怕梨花落尽成秋色。","燕燕飞来，问春何在，唯有池塘自碧。"]},{"t":"石湖仙","f":"other","p":["松江烟浦。","是千古三高，游衍佳处。","须信石湖仙，似鸱夷、翩然引去。","浮云安在，我自爱、绿香红舞。","容与。","看世间、几度今古。","卢沟旧曾驻马，为黄花、闲吟秀句。","见说胡儿，也学纶巾敧雨。","玉友金蕉，玉人金缕。","缓移筝柱。","闲好语。","明年定在槐府。"]},{"t":"暗香","f":"other","p":["旧时月色。","算几番照我，梅边吹笛。","唤起玉人，不管清寒与攀摘。","何逊而今渐老，都忘却、春风词笔。","但怪得、竹外疏花，香冷入瑶席。","江国。","正寂寂。","叹寄与路遥，夜雪初积。","翠尊易泣。","红萼无言耿相忆。","长记曾携手处，千树压、西湖寒碧。","又片片、吹尽也，几时见得。"]},{"t":"疏影","f":"other","p":["苔枝缀玉。","有翠禽小小，枝上同宿。","客里相逢，篱角黄昏，无言自倚修竹。","昭君不惯胡沙远，但暗忆、江南江北。","想佩环、月夜归来，化作此花幽独。","犹记深宫旧事，那人正睡里，飞近蛾绿。","莫似春风，不管盈盈，早与安排金屋。","还教一片随波去，又却怨、玉龙哀曲。","等恁时、重觅幽香，已入小窗横幅。"]},{"t":"惜红衣","f":"other","p":["簟枕邀凉，琴书换日，睡馀无力。","细洒冰泉，并刀破甘碧。","墙头唤酒，谁问讯、城南诗客。","岑寂。","高柳晚蝉，说西风消息。","虹粱水陌。","鱼浪吹香，红衣半狼藉。","维舟试望故国。","眇天北。","可惜渚边沙外，不共美人游历。","问甚时同赋，三十六陂秋色。"]},{"t":"角招","f":"other","p":["为春瘦。","何堪更绕西湖，尽是垂柳。","自看烟外岫。","记得与君，湖上携手。","君归未久。","早乱落、香红千亩。","一叶凌波缥缈，过三十六离宫，遣游人回首。","犹有。","画船障袖。","青楼倚扇，相映人争秀。","翠翘光欲溜。","爱著宫黄，而今时候。","伤春似旧。","荡一点、春心如酒。","写入吴丝自奏。","问谁识，曲中心、花前友。"]},{"t":"徵招","f":"other","p":["潮回却过西陵浦，扁舟仅容居士。","去得几何时，黍离离如此。","客途今倦矣。","漫赢得、一襟诗思。","记忆江南，落帆沙际，此行还是。","迤逦。","剡中山，重相见、依依故人情味。","似怨不来游，拥愁鬟十二。","一丘聊复尔。","也孤负、幼舆高志。","水葓晚，漠漠摇烟，奈未成归计。"]},{"t":"秋宵吟","f":"other","p":["古帘空，坠月皎。","坐久西窗人悄。","蛩吟苦，渐漏水丁丁，箭壶催晓。","引凉飔、动翠葆。","露脚斜飞云表。","因嗟念，似去国情怀，暮帆烟草。","带眼销磨，为近日、愁多顿老。","卫娘何在，宋玉归来，两地暗萦绕。","摇落江枫早。","嫩约无凭，幽梦又杳。","但盈盈、泪洒单衣，今夕何夕恨未了。"]},{"t":"凄凉犯","f":"other","p":["绿杨巷陌。","秋风起、边城一片离索。","马嘶渐远，人归甚处，戍楼吹角。","情怀正恶。","更衰草寒烟淡薄。","似当时、将军部曲，迤逦度沙漠。","追念西湖上，小舫携歌，晚花行乐。","旧游在否，想如今、翠凋红落。","漫写羊裙，等新雁来时系著。","怕匆匆、不肯寄与，误后约。"]},{"t":"翠楼吟","f":"other","p":["月冷龙沙，尘轻虎落，今年汉酺初赐。","新翻胡部曲，听毡幕、元戎歌吹。","层楼高峙。","看栏曲萦红，檐牙飞翠。","人姝丽。","粉香吹下，夜寒风细。","此地。","宜有词仙，拥素云黄鹤，与君游戏。","玉梯凝望久，叹芳草、萋萋千里。","天涯情味。","仗酒襏清愁，花销英气。","西山外。","晚来还卷，一帘秋霁。"]},{"t":"湘月・念奴娇","f":"other","p":["五湖旧约，问经年底事，长负清景。","暝入西山，渐唤我、一叶夷犹乘兴。","倦网都收，归禽时度，月上汀州冷。","中流容与，画桡不点清镜。","谁解唤起湘灵，烟鬟雾鬓，理哀弦鸿阵。","玉麈谈玄，叹坐客、多少风流名胜。","暗柳萧萧，飞星冉冉，夜久知秋信。","鲈鱼应好，旧家乐事谁省。"]},{"t":"小重山令・小重山","f":"other","p":["寒食飞红满帝城。","慈乌相对立，柳青青。","玉阶端笏细陈情。","天恩许，春尽可还京。","鹊报倚门人。","安舆扶上了，更亲擎。","看花携乐缓行程。","争迎处，堂下拜公卿。"]},{"t":"念奴娇","f":"other","p":["昔游未远，记湘皋闻瑟，沣浦捐褋。","因觅孤山林处士，来踏梅根残雪。","獠女供花，伧儿行酒，卧看青门辙。","一丘吾老，可怜情事空切。","曾见海作桑田，仙人云表，笑汝真痴绝。","说与依依王谢燕，应有凉风时节。","越只青山，吴惟芳草，万古皆沈灭。","绕枝三匝，白头歌尽明月。"]},{"t":"卜算子","f":"other","p":["江左咏梅人，梦绕青青路。","因向凌风台下看，心事还将与。","忆别庾郎时，又过林逋处。","万古西湖寂寞春，惆怅谁能赋。"]},{"t":"卜算子","f":"other","p":["月上海云沈，鸥去吴波回。","行过西泠有一枝，竹暗人家静。","又见水沈亭，举目悲风景。","花下铺毡把一杯，缓饮春风影。"]},{"t":"卜算子","f":"other","p":["藓干石斜妨，玉蕊松低覆。","日暮冥冥一见来，略比年时瘦。","凉观酒初醒，竹阁吟才就。","犹恨幽香作许悭，小迟春心透。"]},{"t":"卜算子","f":"other","p":["家在马城西，今赋梅屏雪。","梅雪相兼不见花，月影玲珑彻。","前度带愁看，一饷和愁折。","若使逋仙及见之，定自成愁绝。"]},{"t":"卜算子","f":"other","p":["摘蕊暝禽飞，倚树悬冰落。","下竺桥边浅立时，香已漂流却。","空径晚烟平，古寺春寒恶。","老子寻花第一番，常恐吴儿觉。"]},{"t":"卜算子","f":"other","p":["绿萼更横枝，多少梅花样。","惆怅西村一坞春，开遍无人赏。","细草藉金舆，岁岁长吟想。","枝上么禽一两声，犹似宫娥唱。"]},{"t":"卜算子","f":"other","p":["象笔带香题，龙笛吟春咽。","杨柳娇痴未觉愁，花管人离别。","路出古昌源，石瘦冰霜洁。","折得青须碧藓花，持向人间说。"]},{"t":"卜算子","f":"other","p":["御苑接湖波，松下春风细。","云绿峨峨玉万枝，别有仙风味。","长信昨来看，忆共东皇醉。","此树婆娑一惘然，苔藓生春意。"]},{"t":"洞仙歌","f":"other","p":["花中惯识，压架玲珑雪。","乍见缃蕤间琅叶。","恨春风将了，染额人归，留得个、袅袅垂香带月。","鹅儿真似酒，我爱幽芳，远比酴醿又娇绝。","自种古松根，待看黄龙，乱飞上、苍髯五鬣。","更老仙、添与笔端春，敢唤起桃花，问谁优劣。"]},{"t":"蓦山溪","f":"other","p":["青青官柳，飞过双双燕。","楼上对春寒，卷珠帘、瞥然一见。","如今春去，香絮乱因风，沾径草，惹墙花，一一教谁管。","阳关去也，方表人肠断。","几度拂行轩，念衣冠、尊前易散。","翠眉织锦，红叶浪题诗。","烟渡口，水亭边，长是心先乱。"]},{"t":"永遇乐","f":"other","p":["我与先生，夙期已久，人间无此。","不学杨郎，南山种豆，十一徵微利。","云霄直上，诸公衮衮，乃作道边苦李。","五千言，老来受用，肯教造物儿戏。","东冈记得，同来胥宇，岁月几时难计。","柳老悲桓，松高对阮。","未办为邻地。","长干白下，青楼朱阁，往往梦中槐蚁。","却不如、洼尊放满，老夫未醉。"]},{"t":"虞美人","f":"other","p":["阑干表立苍龙背。","三面巉天翠。","东游才上小蓬莱。","不见此楼烟雨、未应回。","而今指点来时路。","却是冥濛处。","老仙鹤驭几时归。","未必山川城郭、是耶非。"]},{"t":"永遇乐","f":"other","p":["云隔迷楼，苔封很石，人向何处。","数骑秋烟，一篙寒汐，千古空来去。","使君心在，苍厓绿嶂，苦被北门留住。","有尊中酒差可饮，大旗尽绣熊虎。","前身诸葛，来游此地，数语便酬三顾。","楼外冥冥，江皋隐隐，认得征西路。","中原生聚，神京耆老，南望长淮金鼓。","问当时、依依种柳，至今在否。"]},{"t":"水调歌头","f":"other","p":["日落爱山紫，沙涨省潮回。","平生梦犹不到，一叶眇西来。","欲讯桑田成海，人世了无知者，鱼鸟两相推。","天外玉笙杳，子晋只空台。","倚阑干，二三子，总仙才。","尔歌远游章句，云气入吾杯。","不问王郎五马，颇忆谢生双屐，处处长青苔。","东望赤城近，吾兴亦悠哉。"]},{"t":"汉宫春","f":"other","p":["云曰归欤。","纵垂天曳曳，终反衡庐。","扬州十年一梦，俯仰差殊。","秦碑越殿，悔旧游、作计全疏。","分付与、高怀老尹，管弦丝竹宁无。","知公爱山入剡，若南寻李白，问讯何如。","年年雁飞波上，愁亦关予。","临皋领客，向月边、携酒携鲈。","今但借、秋风一榻，公歌我亦能书。"]},{"t":"汉宫春","f":"other","p":["一顾倾吴。","苎萝人不见，烟杳重湖。","当时事如对弈，此亦天乎。","大夫仙去，笑人间、千古须臾。","有倦客、扁舟夜泛，犹疑水鸟相呼。","秦山对楼自绿，怕越王故垒，时下樵苏。","只今倚阑一笑，然则非欤。","小丛解唱，倩松风、为我吹竽。","更坐待、千岩月落，城头眇眇啼鸟。"]},{"t":"点绛唇","f":"other","p":["祝寿筵开，画堂深映花如绣。","瑞烟喷兽。","帘幕香风透。","一点台星，化作人间秀。","韶音奏。","两行红袖。","齐劝长生酒。"]},{"t":"越女镜心・法曲献仙音","f":"other","p":["风竹吹香，水枫鸣绿，睡觉凉生金缕。","镜底同心，枕前双玉，相看转伤幽素。","傍绮阁、轻阴度。","飞来鉴湖雨。","近重午。","燎银篝、暗薰溽暑。","罗扇小、空写数行怨苦。","纤手结芳兰，且休歌、九辩怀楚。","故国情多，对溪山、都是离绪。","但一川烟苇，恨满西陵归路。"]},{"t":"月上海棠","f":"other","p":["红妆艳色，照浣花溪影，绝代姝丽。","弄轻风、摇荡满林罗绮。","自然富贵天姿，都不比、等闲桃李。","帘栊静悄，月上正贪春睡。","长记初开日，逞妖丽、如与人面争媚。","过韶光一瞬，便成流水。","对此日叹浮华，惜芳菲、易成憔悴。","留无计。","惟有花边尽醉。"]}],"cp-2c570fb3":[{"t":"醉太平","f":"other","p":["冰肌玉容。","情真意浓。","小楼几度春风。","醉琉璃酒钟。","关山万重。","何时又逢。","思量雨迹云踪。","似襄王梦中。"]}],"cp-bf841349":[{"t":"玉楼春","f":"other","p":["姑苏台上春光发。","菊老寒轻香未歇。","人言太守是龚黄，天为吾君生稷契。","月良庆会俱良月。","万岁千秋同瑞节。","明朝仙领趣提鳌，十万人家齐卧辙。"]},{"t":"玉楼春","f":"other","p":["蟠桃十月惊春早。","春到玉梅枝上小。","和羹人物应时生，天上骑鲸生凤沼。","万家宝篆祥烟晓。","竞祝史君长不老。","夜来南极照元台，见说沙堤新筑了。"]}]}